Workbook
Name \0: #REF!
Name \b: #N/A
Name \C: #REF!
Name \C: #REF!
Name \C: #REF!
Name \C: #REF!
Name \c1: #REF!
Name \c1: #REF!
Name \c1: #REF!
Name \c1: #REF!
Name \c2: #REF!
Name \c2: #REF!
Name \c2: #REF!
Name \c2: #REF!
Name \D: #REF!
Name \D: #REF!
Name \D: #REF!
Name \D: #REF!
Name \l: #REF!
Name \l: #REF!
Name \l: #REF!
Name \l: #REF!
Name \M: #REF!
Name \M: #REF!
Name \M: #REF!
Name \M: #REF!
Name \N: #REF!
Name \N: #REF!
Name \N: #REF!
Name \N: #REF!
Name \p: #REF!
Name \p: #REF!
Name \p: #REF!
Name \p: #REF!
Name \R: #REF!
Name \R: #REF!
Name \R: #REF!
Name \R: #REF!
Name \S: #REF!
Name \S: #REF!
Name \S: #REF!
Name \S: #REF!
Name \U: #REF!
Name \U: #REF!
Name \U: #REF!
Name \U: #REF!
Name \V: #REF!
Name \V: #REF!
Name \V: #REF!
Name \V: #REF!
Name \x: #REF!
Name \x: #REF!
Name \x: #REF!
Name \x: #REF!
Name _: "tcap"
Name _\wdr: #REF!
Name _\wdr: #REF!
Name _\wdr: #REF!
Name _\wdr: #REF!
Name __________________________________aaa5: #REF!

Sheet BOQ
A1: Construction of check dam across Marudhaiyar river at Varanavasi village in Ariyalur Taluk and District
A2: BOQ Abstract
A3: Sno | B3: Item Description | C3: Quantity | D3: Units | E3: Basic Rate | F3: Amount
A4: 1 | B4: Clearing Scrub jungle and destroying them effectively etc. complete complying with Standard Specifications and as directed by the Departmental Engineers. | C4: 25849.6 | D4: sqm | E4: 6 | F4: =C4*E4 -> 155097.6
A5: 2 | B5: Earthwork excavation for foundation in all kind of soils and sub soils to full depth except hardrock,medium rock,requiring blasting inclusive of shoring,strutting and bailing out water wherever necessary,refilling the sides of foundation with excavated earth in layers of not more than 15cm thick well rammed and compacted and depositing the surplus excavated earth in places shown by the departmental officers with initial lead of 10 meters and initial lift of 2 meters clearing and levelling the site complete complying with standard specifications and as directed by the Departmental Engineers. (Narrow excavation) | C5: 5254 | D5: cum | E5: 226 | F5: =C5*E5 -> 1187404
A6: 3 | B6: Earth work excavating and depositing on bank with initial lead of 10 metres and lift of 2 metres in sand silt or other loose soil, wet sand or silt not under water light black cotton soil sandy loam and ordinary soil including excavated earth ordinary soil etc. complete complying with Standard Specifications and as directed by the Departmental Engineers.SS 20 A. (Open Excavation.) | C6: 29381 | D6: cum | E6: 85 | F6: =C6*E6 -> 2497385
A7: 4 | B7: Supplying and erection of steel centering for sides and soffits with strutting up to 3m height for plain surface with all cross bracings using Mild Steel sheets of size 90cm. X 60cm. thickness of and B.G.10 stiffened with welded Mild Steel angles of size 25 X 25 X 3mm for boarding, laid over country wood joists of size 10cmX 6.5cm spaced at 90cm. Centre to centre and supported by casuarina props of 10 to 13cm dia (spaced at 75cm) Centre to centre etc. complete complying with Standard Specifications and as directed by the Departmental Engineers. | F7: =C7*E7 -> 0
A8: 4.01 | B8: Centering without strutting Below ground level | C8: 6346 | D8: sqm | E8: 955 | F8: =C8*E8 -> 6060430
A9: 4.02 | B9: Centering with strutting upto 3m height | C9: 6536 | D9: sqm | E9: 1060 | F9: =C9*E9 -> 6928160
A10: 4.03 | B10: Centering with strutting 3-4m height | C10: 739 | D10: sqm | E10: 1095 | F10: =C10*E10 -> 809205
A11: 4.04 | B11: Centering with strutting 4-5m height | C11: 303 | D11: sqm | E11: 1130 | F11: =C11*E11 -> 342390
A12: 5 | B12: Providing and placing Plain cement concrete M10 grade using crushed broken hard granite course aggregate (well Graded) of Nominal maximum size of 40mm to Ls specified grading (to achieve the specified characteristicik strength of 10N /mm2 in 28 days) and mixing the ingredients in approved mixer including dewatering of the placement site by baling (pumping and dewatering wherever necess eng placing in layers and vibrating water curing finishing hte surface with all leades and lifts etc. complete complying with Standard Specifications and as directed by the Departmental Engineers. | C12: 379 | D12: cum | E12: 5885 | F12: =C12*E12 -> 2230415
A13: 6 | B13: Providing and placing in position of plain cement concrete M15 using 20 mm size hard blue granite broken stone jelly with M.Sand mixing with mixer machine including the cost of bailing/pumping wherever necessary laying the concrete in layers of not exceeding 15 cm thick, compacting, consolidation, vibratring,finishing, watering, curing etc. complete complying with Standard Specifications and as directed by the Departmental Engineers. | F13: =C13*E13 -> 0
A14: 6.01 | B14: Below ground level upto 1.50 m | C14: 739 | D14: cum | E14: 6850 | F14: =C14*E14 -> 5062150
A15: 6.02 | B15: Below ground level-Foundation upto 1.50 m to 4.50 m | C15: 220 | D15: cum | E15: 6984 | F15: =C15*E15 -> 1536480
A16: 7 | B16: Providing and placing in position of plain cement concrete M15 grade using 60% of 40mm size hard blue granite broken stone jelly and 40% of 20mm size hard blue granite broken stone jelly with M.Sand mixing with mixer machine including the cost of bailing/pumping wherever necessary laying the concrete in layers of not exceeding 15 cm thick, compacting, consolidation,vibrating,finishing, watering, curing etc. complete complying with Standard Specifications and as directed by the Departmental Engineers. | F16: =C16*E16 -> 0
A17: 7.01 | B17: Below ground level up to 1.50 m | C17: 4986 | D17: cum | E17: 6510 | F17: =C17*E17 -> 32458860
A18: 7.02 | B18: Above ground level up to 4.50 m | C18: 1579 | D18: cum | E18: 6645 | F18: =C18*E18 -> 10492455
A19: 8 | B19: Supplying and fabrication and CC Block of size 1.50 X 1.50 X 0.90 m with Plain Cement Concrete 1:2:4 (one cement two m.sand and Four aggregate) using 40mm and down graded metal hard broken stone jelly for foundation including dewatering if found necessary and placing in position including ramming watering and curing etc. complete complying with Standard Specifications and as directed by the Departmental Engineers. | C19: 800 | D19: Nos | E19: 14577 | F19: =C19*E19 -> 11661600
A20: 9 | B20: Providing and laying in position standardised concrete Mix M-20 Grade in accordance with IS 456-2000 using 20mm and downgraded hard broken granite stone jelly for all RCC items of works with minium cement content of 325 kg/m3 and maxium water cement ratio of 0.55 including admixture (Plasticizer/Super plasticizer) in recommended proportions asper IS 9103 to accelerate, retard setting of concrete, improve workability without imparing strength and durability with about (5 cu.m) 7730 kg of 20 mm machine crushed stone jelly and with about (4.79 cu.m) 7670 kg of m.sand, but excluding cost of reinforcemnt grill and fabricating charges, centering and shuttering and also including and laying, vibrating with mechanical vibrators, finishing, curing etc. complete complying with Standard Specifications and as directed by the Departmental Engineers. | C20: 906 | D20: cum | E20: 8709 | F20: =C20*E20 -> 7890354
A21: 10 | B21: Reinforced cement concrete M25 using 20mm hard broken stone jelly and downgreded to IS specified grading mixed in mixer machine including dewatering the placement site, laying the concrete in layers and in bays.vibrating compacting and finishing the surface with all lead and lifts, watering curing complete to attain the profile and strength as specified in the drawings and specification for various lengths and heights below and above ground level etc. complete complying with Standard Specifications and as directed by the Departmental Engineers. | C21: 32 | D21: cum | E21: 8857 | F21: =C21*E21 -> 283424
A22: 11 | B22: Providing and placing plain cement concrete M20 grade using crusher broken hard granite course agrregate (well graded) of nominal maximum size of 20mm to specified grading to achieve the special characteristic strength of 20 N/mm2 in 28 days and mixing the ingredients in approved mixed placing in layers and vibrating water curing finishing the surface with all leads and lifts etc. complete in all respects so as to attain the profile strength specified in the approved drawing and specified in the approved drawing and specifications as per the direction of the engineer incharge of works and etc. complete complying with Standard Specifications and as directed by the Departmental Engineers. | F22: =C22*E22 -> 0
A23: 11.01 | B23: Below ground level up to 1.50 m | C23: 225 | D23: cum | E23: 7280 | F23: =C23*E23 -> 1638000
A24: 11.02 | B24: Below ground level 1.50m to upto 4.50 m | C24: 525 | D24: cum | E24: 7414 | F24: =C24*E24 -> 3892350
A25: 11.03 | B25: Above ground level upto 4.50m | C25: 2.9 | D25: cum | E25: 7416 | F25: =C25*E25 -> 21506.4
A26: 12 | B26: Supplying fabricating and placing in position of Mild Steel (MS) or Ribbed Tor Steel (RTS) of grills for all R C C works including cost of steel, binding wire and labour charges for decoiling cutting, bending and tying the grills etc. complete complying with standard specifications and as directed by the Departmental Engineers. | C26: 1752 | D26: qtl. | E26: 9258 | F26: =C26*E26 -> 16220016
A27: 13 | B27: Supplying and filling in clean M- sand in layers of not more than 15cm thick well rammed watered and consolidated etc. complete complying with Standard Specifications and as directed by the Departmental Engineers. | C27: 398 | D27: cum | E27: 1785 | F27: =C27*E27 -> 710430
A28: 14 | B28: Supplying and filling for inverted filter arrangements below CC blocks with 40 cm thick graded inverted filter provided in two or more layers (ie 20 mm, 40 mm, 63 mm.) size metal provided using HBGS jelly conveyance upto 100 m etc. complete complying with Standard Specifications and as directed by the Departmental Engineers. | C28: 795 | D28: cum | E28: 1580 | F28: =C28*E28 -> 1256100
A29: 15 | B29: Supplying and Filling of Gravel in between the gap of CC Block with 75mm thick,etc. complete complying with Standard Specifications and as directed by the Departmental Engineers. | C29: 345 | D29: cum | E29: 447 | F29: =C29*E29 -> 154215
A30: 16 | B30: Supplying and filling loose boulders of Size more than 300mm and weight more than 40kg in U/S and D/S apron using including conveyance,cost of materials etc. complete complying with standard specifications and as directed by the Departmental Engineers | C30: 4440 | D30: cum | E30: 2614 | F30: =C30*E30 -> 11606160
A31: 17 | B31: Rough stone dry packing using new stones for cone wrapping aprons and revetment including labour charges etc. complete complying with Standard Specifications and as directed by the Departmental Engineers. (.Cone Wrapping) | C31: 1099 | D31: cum | E31: 2315 | F31: =C31*E31 -> 2544185
A32: 18 | B32: Jeddy stone packing using new stones u/s stone pitching including labour charges etc. complete complying with Standard Specifications and as directed by the Departmental Engineers. | C32: 450 | D32: cum | E32: 2614 | F32: =C32*E32 -> 1176300
A33: 19 | B33: Design, fabrication, supply, errection, testing and commissioning of fixed wheel type vertical lift gate(with top seal) consisting of skin plate, stiffeners, horizontal and vertical girders, wheels, guide rollers, rubber seals etc., with all accessories for canal escape/regulator vent including cost of materials, machinery, labour, cutting, aligning, welding, finishing, cleaning, applying one coat of zinc rich epoxy primer and three coats of cold applied coal tar epoxy paint,seal fixing etc., complete as per specifications and approved drawings with lead up to 1km and all lifts for structural steel components and all leads and all lifts including packing/forwarding charges for other materials. | C33: 4.44 | D33: tonne | E33: 233491 | F33: =C33*E33 -> 1036700
A34: 20 | B34: Design, fabrication, supply, errection, testing and commissioning of supporting structure, platform, railing, ladder etc., with all accessories for operating canal escape/regulator gate including cost of all materials, machinery, labour, cutting, aligning, welding, finishing, cleaning, greasing, applying two coats of zinc chromate red oxide primer and three coats of approved synthetic enamel paint etc., complete as per specifications and approved drawings with lead up to 1km and all lifts for structural steel components and all leads and all lifts including packing/forwarding charges for other materials. | C34: 3.6 | D34: tonne | E34: 59143 | F34: =C34*E34 -> 212914.8
... A42: 28 | B42: Supplying Demarcation RCC Pre cast Post in Cement Concrete of Grade M15 with well graded aggregates and the nominal maximum size of course aggregate of size 20 mm of size 0.20 x 0.20 x 1.45 M and fixing the Post 40 Cm depth below Ground level, the Post includes using 4 Nos of 10mm RTS Main rod to a length of 1.325 M, using 8 mm MS 10 Nos as Strips with Steel Centring and Painting the Post with Enamel Paint to a Height of 0.80 m around the post etc., complete and Conveying the post to the Site of Demarcation Boundary such as Tank Bund and foreshore including earthwork excavation for Foundation in HSC having the base Plain cement Concrete of 10 Cm of cement concrete M7.5 using Hard blue granite broken stone of graded metal of 40 mm and the Post embeded using Cement Concrete of Grade Cement Concrete M10 with well graded aggregates and the Nominal maximum size of course aggregate of 20 mm etc., complete as directed by the Engineer in charge of works and as per the Technical Specfications | C42: 150 | D42: Nos | E42: 1697 | F42: =C42*E42 -> 254550
B43: Total = | F43: =SUM(F4:F42) -> 1.9847417e+08
B44: GST at 18% = | E44: 0 | F44: =F43*0.18 -> 35725351
B45: Grand Total = | F45: =SUM(F43:F44) -> 2.3419952e+08
F49: =F45+6807707 -> 2.4100723e+08
F50: =F49-F45 -> 6807707
F51: =F50/F45 -> 0.02906798

Sheet BOQ Major
A1: Construction of check dam across Marudhaiyar river at Varanavasi village in Ariyalur Taluk and District | G1: % from Total Value
A2: BOQ Abstract - Major items
A3: Sno | B3: Item Description | C3: Quantity | D3: Units | E3: Basic Rate | F3: Amount
A4: 1 | B4: Clearing Scrub jungle and destroying them effectively etc. complete complying with Standard Specifications and as directed by the Departmental Engineers. | C4: 25849.6 | D4: sqm | E4: 6 | F4: =C4*E4 -> 155097.6 | G4: =F4/$F$43 -> 0.00078144979
A5: 2 | B5: Earthwork excavation for foundation in all kind of soils and sub soils to full depth except hardrock,medium rock,requiring blasting inclusive of shoring,strutting and bailing out water wherever necessary,refilling the sides of foundation with excavated earth in layers of not more than 15cm thick well rammed and compacted and depositing the surplus excavated earth in places shown by the departmental officers with initial lead of 10 meters and initial lift of 2 meters clearing and levelling the site complete complying with standard specifications and as directed by the Departmental Engineers. (Narrow excavation) | C5: 5254 | D5: cum | E5: 226 | F5: =C5*E5 -> 1187404 | G5: =F5/$F$43 -> 0.0059826626
A6: 3 | B6: Earth work excavating and depositing on bank with initial lead of 10 metres and lift of 2 metres in sand silt or other loose soil, wet sand or silt not under water light black cotton soil sandy loam and ordinary soil including excavated earth ordinary soil etc. complete complying with Standard Specifications and as directed by the Departmental Engineers.SS 20 A. (Open Excavation.) | C6: 29381 | D6: cum | E6: 85 | F6: =C6*E6 -> 2497385 | G6: =F6/$F$43 -> 0.012582922
A7: 4 | B7: Supplying and erection of steel centering for sides and soffits with strutting up to 3m height for plain surface with all cross bracings using Mild Steel sheets of size 90cm. X 60cm. thickness of and B.G.10 stiffened with welded Mild Steel angles of size 25 X 25 X 3mm for boarding, laid over country wood joists of size 10cmX 6.5cm spaced at 90cm. Centre to centre and supported by casuarina props of 10 to 13cm dia (spaced at 75cm) Centre to centre etc. complete complying with Standard Specifications and as directed by the Departmental Engineers. | F7: =C7*E7 -> 0 | G7: =F7/$F$43 -> 0
A8: 4.01 | B8: Centering without strutting Below ground level | C8: 6346 | D8: sqm | E8: 955 | F8: =C8*E8 -> 6060430 | G8: =F8/$F$43 -> 0.030535107
A9: 4.02 | B9: Centering with strutting upto 3m height | C9: 6536 | D9: sqm | E9: 1060 | F9: =C9*E9 -> 6928160 | G9: =F9/$F$43 -> 0.034907111
A10: 4.03 | B10: Centering with strutting 3-4m height | C10: 739 | D10: sqm | E10: 1095 | F10: =C10*E10 -> 809205 | G10: =F10/$F$43 -> 0.00407713
A11: 4.04 | B11: Centering with strutting 4-5m height | C11: 303 | D11: sqm | E11: 1130 | F11: =C11*E11 -> 342390 | G11: =F11/$F$43 -> 0.0017251111
A12: 5 | B12: Providing and placing Plain cement concrete M10 grade using crushed broken hard granite course aggregate (well Graded) of Nominal maximum size of 40mm to Ls specified grading (to achieve the specified characteristicik strength of 10N /mm2 in 28 days) and mixing the ingredients in approved mixer including dewatering of the placement site by baling (pumping and dewatering wherever necess eng placing in layers and vibrating water curing finishing hte surface with all leades and lifts etc. complete complying with Standard Specifications and as directed by the Departmental Engineers. | C12: 379 | D12: cum | E12: 5885 | F12: =C12*E12 -> 2230415 | G12: =F12/$F$43 -> 0.01123781
A13: 6 | B13: Providing and placing in position of plain cement concrete M15 using 20 mm size hard blue granite broken stone jelly with M.Sand mixing with mixer machine including the cost of bailing/pumping wherever necessary laying the concrete in layers of not exceeding 15 cm thick, compacting, consolidation, vibratring,finishing, watering, curing etc. complete complying with Standard Specifications and as directed by the Departmental Engineers. | F13: =C13*E13 -> 0 | G13: =F13/$F$43 -> 0
A14: 6.01 | B14: Below ground level upto 1.50 m | C14: 739 | D14: cum | E14: 6850 | F14: =C14*E14 -> 5062150 | G14: =F14/$F$43 -> 0.025505334
A15: 6.02 | B15: Below ground level-Foundation upto 1.50 m to 4.50 m | C15: 220 | D15: cum | E15: 6984 | F15: =C15*E15 -> 1536480 | G15: =F15/$F$43 -> 0.0077414607
A16: 7 | B16: Providing and placing in position of plain cement concrete M15 grade using 60% of 40mm size hard blue granite broken stone jelly and 40% of 20mm size hard blue granite broken stone jelly with M.Sand mixing with mixer machine including the cost of bailing/pumping wherever necessary laying the concrete in layers of not exceeding 15 cm thick, compacting, consolidation,vibrating,finishing, watering, curing etc. complete complying with Standard Specifications and as directed by the Departmental Engineers. | F16: =C16*E16 -> 0 | G16: =F16/$F$43 -> 0
A17: 7.01 | B17: Below ground level up to 1.50 m | C17: 4986 | D17: cum | E17: 6510 | F17: =C17*E17 -> 32458860 | G17: =F17/$F$43 -> 0.16354199
A18: 7.02 | B18: Above ground level up to 4.50 m | C18: 1579 | D18: cum | E18: 6645 | F18: =C18*E18 -> 10492455 | G18: =F18/$F$43 -> 0.052865594
A19: 8 | B19: Supplying and fabrication and CC Block of size 1.50 X 1.50 X 0.90 m with Plain Cement Concrete 1:2:4 (one cement two m.sand and Four aggregate) using 40mm and down graded metal hard broken stone jelly for foundation including dewatering if found necessary and placing in position including ramming watering and curing etc. complete complying with Standard Specifications and as directed by the Departmental Engineers. | C19: 800 | D19: Nos | E19: 14577 | F19: =C19*E19 -> 11661600 | G19: =F19/$F$43 -> 0.05875626
A20: 9 | B20: Providing and laying in position standardised concrete Mix M-20 Grade in accordance with IS 456-2000 using 20mm and downgraded hard broken granite stone jelly for all RCC items of works with minium cement content of 325 kg/m3 and maxium water cement ratio of 0.55 including admixture (Plasticizer/Super plasticizer) in recommended proportions asper IS 9103 to accelerate, retard setting of concrete, improve workability without imparing strength and durability with about (5 cu.m) 7730 kg of 20 mm machine crushed stone jelly and with about (4.79 cu.m) 7670 kg of m.sand, but excluding cost of reinforcemnt grill and fabricating charges, centering and shuttering and also including and laying, vibrating with mechanical vibrators, finishing, curing etc. complete complying with Standard Specifications and as directed by the Departmental Engineers. | C20: 906 | D20: cum | E20: 8709 | F20: =C20*E20 -> 7890354 | G20: =F20/$F$43 -> 0.039755067
A21: 10 | B21: Reinforced cement concrete M25 using 20mm hard broken stone jelly and downgreded to IS specified grading mixed in mixer machine including dewatering the placement site, laying the concrete in layers and in bays.vibrating compacting and finishing the surface with all lead and lifts, watering curing complete to attain the profile and strength as specified in the drawings and specification for various lengths and heights below and above ground level etc. complete complying with Standard Specifications and as directed by the Departmental Engineers. | C21: 32 | D21: cum | E21: 8857 | F21: =C21*E21 -> 283424 | G21: =F21/$F$43 -> 0.0014280145
A22: 11 | B22: Providing and placing plain cement concrete M20 grade using crusher broken hard granite course agrregate (well graded) of nominal maximum size of 20mm to specified grading to achieve the special characteristic strength of 20 N/mm2 in 28 days and mixing the ingredients in approved mixed placing in layers and vibrating water curing finishing the surface with all leads and lifts etc. complete in all respects so as to attain the profile strength specified in the approved drawing and specified in the approved drawing and specifications as per the direction of the engineer incharge of works and etc. complete complying with Standard Specifications and as directed by the Departmental Engineers. | F22: =C22*E22 -> 0 | G22: =F22/$F$43 -> 0
A23: 11.01 | B23: Below ground level up to 1.50 m | C23: 225 | D23: cum | E23: 7280 | F23: =C23*E23 -> 1638000 | G23: =F23/$F$43 -> 0.0082529631
A24: 11.02 | B24: Below ground level 1.50m to upto 4.50 m | C24: 525 | D24: cum | E24: 7414 | F24: =C24*E24 -> 3892350 | G24: =F24/$F$43 -> 0.019611368
A25: 11.03 | B25: Above ground level upto 4.50m | C25: 2.9 | D25: cum | E25: 7416 | F25: =C25*E25 -> 21506.4 | G25: =F25/$F$43 -> 0.00010835868
A26: 12 | B26: Supplying fabricating and placing in position of Mild Steel (MS) or Ribbed Tor Steel (RTS) of grills for all R C C works including cost of steel, binding wire and labour charges for decoiling cutting, bending and tying the grills etc. complete complying with standard specifications and as directed by the Departmental Engineers. | C26: 1752 | D26: qtl. | E26: 9258 | F26: =C26*E26 -> 16220016 | G26: =F26/$F$43 -> 0.081723561
A27: 13 | B27: Supplying and filling in clean M- sand in layers of not more than 15cm thick well rammed watered and consolidated etc. complete complying with Standard Specifications and as directed by the Departmental Engineers. | C27: 398 | D27: cum | E27: 1785 | F27: =C27*E27 -> 710430 | G27: =F27/$F$43 -> 0.0035794582
A28: 14 | B28: Supplying and filling for inverted filter arrangements below CC blocks with 40 cm thick graded inverted filter provided in two or more layers (ie 20 mm, 40 mm, 63 mm.) size metal provided using HBGS jelly conveyance upto 100 m etc. complete complying with Standard Specifications and as directed by the Departmental Engineers. | C28: 795 | D28: cum | E28: 1580 | F28: =C28*E28 -> 1256100 | G28: =F28/$F$43 -> 0.0063287832
A29: 15 | B29: Supplying and Filling of Gravel in between the gap of CC Block with 75mm thick,etc. complete complying with Standard Specifications and as directed by the Departmental Engineers. | C29: 345 | D29: cum | E29: 447 | F29: =C29*E29 -> 154215 | G29: =F29/$F$43 -> 0.00077700287
A30: 16 | B30: Supplying and filling loose boulders of Size more than 300mm and weight more than 40kg in U/S and D/S apron using including conveyance,cost of materials etc. complete complying with standard specifications and as directed by the Departmental Engineers | C30: 4440 | D30: cum | E30: 2614 | F30: =C30*E30 -> 11606160 | G30: =F30/$F$43 -> 0.058476929
A31: 17 | B31: Rough stone dry packing using new stones for cone wrapping aprons and revetment including labour charges etc. complete complying with Standard Specifications and as directed by the Departmental Engineers. (.Cone Wrapping) | C31: 1099 | D31: cum | E31: 2315 | F31: =C31*E31 -> 2544185 | G31: =F31/$F$43 -> 0.012818721
A32: 18 | B32: Jeddy stone packing using new stones u/s stone pitching including labour charges etc. complete complying with Standard Specifications and as directed by the Departmental Engineers. | C32: 450 | D32: cum | E32: 2614 | F32: =C32*E32 -> 1176300 | G32: =F32/$F$43 -> 0.0059267158
A33: 19 | B33: Design, fabrication, supply, errection, testing and commissioning of fixed wheel type vertical lift gate(with top seal) consisting of skin plate, stiffeners, horizontal and vertical girders, wheels, guide rollers, rubber seals etc., with all accessories for canal escape/regulator vent including cost of materials, machinery, labour, cutting, aligning, welding, finishing, cleaning, applying one coat of zinc rich epoxy primer and three coats of cold applied coal tar epoxy paint,seal fixing etc., complete as per specifications and approved drawings with lead up to 1km and all lifts for structural steel components and all leads and all lifts including packing/forwarding charges for other materials. | C33: 4.44 | D33: tonne | E33: 233491 | F33: =C33*E33 -> 1036700 | G33: =F33/$F$43 -> 0.0052233499
A34: 20 | B34: Design, fabrication, supply, errection, testing and commissioning of supporting structure, platform, railing, ladder etc., with all accessories for operating canal escape/regulator gate including cost of all materials, machinery, labour, cutting, aligning, welding, finishing, cleaning, greasing, applying two coats of zinc chromate red oxide primer and three coats of approved synthetic enamel paint etc., complete as per specifications and approved drawings with lead up to 1km and all lifts for structural steel components and all leads and all lifts including packing/forwarding charges for other materials. | C34: 3.6 | D34: tonne | E34: 59143 | F34: =C34*E34 -> 212914.8 | G34: =F34/$F$43 -> 0.0010727582
... A42: 28 | B42: Supplying Demarcation RCC Pre cast Post in Cement Concrete of Grade M15 with well graded aggregates and the nominal maximum size of course aggregate of size 20 mm of size 0.20 x 0.20 x 1.45 M and fixing the Post 40 Cm depth below Ground level, the Post includes using 4 Nos of 10mm RTS Main rod to a length of 1.325 M, using 8 mm MS 10 Nos as Strips with Steel Centring and Painting the Post with Enamel Paint to a Height of 0.80 m around the post etc., complete and Conveying the post to the Site of Demarcation Boundary such as Tank Bund and foreshore including earthwork excavation for Foundation in HSC having the base Plain cement Concrete of 10 Cm of cement concrete M7.5 using Hard blue granite broken stone of graded metal of 40 mm and the Post embeded using Cement Concrete of Grade Cement Concrete M10 with well graded aggregates and the Nominal maximum size of course aggregate of 20 mm etc., complete as directed by the Engineer in charge of works and as per the Technical Specfications | C42: 150 | D42: Nos | E42: 1697 | F42: =C42*E42 -> 254550 | G42: =F42/$F$43 -> 0.0012825346
B43: Total = | F43: =SUM(F4:F42) -> 1.9847417e+08 | G43: =F43/$F$43 -> 1
B44: GST at 18% = | E44: 0 | F44: =F43*0.18 -> 35725351
B45: Grand Total = | F45: =SUM(F43:F44) -> 2.3419952e+08
F49: =F45+6807707 -> 2.4100723e+08
F50: =F49-F45 -> 6807707
F51: =F50/F45 -> 0.02906798

Sheet Top Sheet
B2: ZERO COST ESTIMATE - SUMMARY
C3: Project: | D3: =BOQ!A1 -> Construction of check dam across Marudhaiyar river at Varanavasi village in Ariyalur Taluk and District
C4: Client: | D4: WRO
C5: Location: | D5: Pattukkottai Taluk
C6: Contractual Completion Duration: | D6: 12 months
C7: Considered Completion Duration: | D7: 12 months
B9: Sl. No. | C9: Description | F9: Amount (in Rs)
B11: 1 | C11: COSTS
B12: a) | C12: Direct Cost | F12: ='BOQ Split'!N43 -> 1.2975679e+08
B13: b) | C13: Indirect Cost | D13: OH | E13: 10476 | F13: =IDC!G77 -> 8768170.9 | J13: =13750*11 -> 151250
B14: 2 | C14: TOTAL COST (DC+IDC) | F14: =SUM(F12:F13) -> 1.3852496e+08
B16: 3 | C16: CONTRACT VALUE (SALES) | D16: (Excluding GST & LC) | F16: ='BOQ Split'!F43 -> 1.9847417e+08
B18: 4 | C18: GROSS MARGIN | F18: =+F16-F14 -> 59949214
B20: 5 | C20: ESCALATION BENEFITS @ 2% | F20: =F12*0% -> 0
B22: 6 | C22: TOTAL MARGIN (4+5) | F22: =SUM(F18:F20) -> 59949214
B24: 7 | C24: Risk & Contingency | F24: 0.01
B25: 8 | C25: Interest Charges | F25: 0
B26: 9 | C26: Insurance Charges | F26: 0
B27: 10 | C27: Bank Guarantee | F27: 0
B29: 11 | C29: GM % | F29: =+F22/F16-F24-F25-F26-F27 -> 0.29205046
B30: 12 | C30: Others
C31: HO Overheads | F31: 0.02
B33: 13 | C33: PBT | F33: =F29-SUM(F31:F31) -> 0.27205046
B38: Remarks:
B40: Prepared by: | E40: Reviewed by:

Sheet BOQ Split
A1: Construction of check dam across Marudhaiyar river at Varanavasi village in Ariyalur Taluk and District
A2: BOQ Abstract
A3: Sno | B3: Item Description | C3: Quantity | D3: Units | E3: Basic Rate | F3: Amount | H3: Materials | I3: Machinery | J3: Fuel | K3: S/C | L3: Labour | M3: Total Rate | N3: Amount | O3: Variance | P3: Materials | Q3: Machinery | R3: Fuel | S3: S/C | T3: Labour
A4: 1 | B4: Clearing Scrub jungle and destroying them effectively etc. complete complying with Standard Specifications and as directed by the Departmental Engineers. | C4: 25849.6 | D4: sqm | E4: 6 | F4: =C4*E4 -> 155097.6 | I4: =RA!F10 -> 7.8159222 | J4: =RA!F13 -> 3.4092597 | L4: =RA!F16 -> 0.46035529 | M4: =SUM(H4:L4) -> 11.685537 | N4: =M4*C4 -> 302066.46 | O4: =F4-N4 -> -146968.86 | P4: =H4*C4 -> 0 | Q4: =I4*C4 -> 202038.46 | R4: =J4*C4 -> 88128 | S4: =K4*C4 -> 0 | T4: =L4*C4 -> 11900
A5: 2 | B5: Earthwork excavation for foundation in all kind of soils and sub soils to full depth except hardrock,medium rock,requiring blasting inclusive of shoring,strutting and bailing out water wherever necessary,refilling the sides of foundation with excavated earth in layers of not more than 15cm thick well rammed and compacted and depositing the surplus excavated earth in places shown by the departmental officers with initial lead of 10 meters and initial lift of 2 meters clearing and levelling the site complete complying with standard specifications and as directed by the Departmental Engineers. (Narrow excavation) | C5: 5254 | D5: cum | E5: 226 | F5: =C5*E5 -> 1187404 | I5: =RA!F26 -> 122.98322 | J5: =RA!F29 -> 105.24553 | L5: =RA!F32 -> 15.987819 | M5: =SUM(H5:L5) -> 244.21657 | N5: =M5*C5 -> 1283113.8 | O5: =F5-N5 -> -95709.846 | P5: =H5*C5 -> 0 | Q5: =I5*C5 -> 646153.85 | R5: =J5*C5 -> 552960 | S5: =K5*C5 -> 0 | T5: =L5*C5 -> 84000
A6: 3 | B6: Earth work excavating and depositing on bank with initial lead of 10 metres and lift of 2 metres in sand silt or other loose soil, wet sand or silt not under water light black cotton soil sandy loam and ordinary soil including excavated earth ordinary soil etc. complete complying with Standard Specifications and as directed by the Departmental Engineers.SS 20 A. (Open Excavation.) | C6: 29381 | D6: cum | E6: 85 | F6: =C6*E6 -> 2497385 | I6: =RA!F42 -> 21.992235 | J6: =RA!F45 -> 21.957047 | L6: =RA!F48 -> 2.8589905 | M6: =SUM(H6:L6) -> 46.808272 | N6: =M6*C6 -> 1375273.8 | O6: =F6-N6 -> 1122111.2 | P6: =H6*C6 -> 0 | Q6: =I6*C6 -> 646153.85 | R6: =J6*C6 -> 645120 | S6: =K6*C6 -> 0 | T6: =L6*C6 -> 84000
A7: 4 | B7: Supplying and erection of steel centering for sides and soffits with strutting up to 3m height for plain surface with all cross bracings using Mild Steel sheets of size 90cm. X 60cm. thickness of and B.G.10 stiffened with welded Mild Steel angles of size 25 X 25 X 3mm for boarding, laid over country wood joists of size 10cmX 6.5cm spaced at 90cm. Centre to centre and supported by casuarina props of 10 to 13cm dia (spaced at 75cm) Centre to centre etc. complete complying with Standard Specifications and as directed by the Departmental Engineers. | F7: =C7*E7 -> 0 | M7: =SUM(H7:L7) -> 0 | N7: =M7*C7 -> 0 | O7: =F7-N7 -> 0 | P7: =H7*C7 -> 0 | Q7: =I7*C7 -> 0 | R7: =J7*C7 -> 0 | S7: =K7*C7 -> 0 | T7: =L7*C7 -> 0
A8: 4.01 | B8: Centering without strutting Below ground level | C8: 6346 | D8: sqm | E8: 955 | F8: =C8*E8 -> 6060430 | K8: =RA!F55 -> 494.96 | L8: =K8*0.05 -> 24.748 | M8: =SUM(H8:L8) -> 519.708 | N8: =M8*C8 -> 3298067 | O8: =F8-N8 -> 2762363 | P8: =H8*C8 -> 0 | Q8: =I8*C8 -> 0 | R8: =J8*C8 -> 0 | S8: =K8*C8 -> 3141016.2 | T8: =L8*C8 -> 157050.81
A9: 4.02 | B9: Centering with strutting upto 3m height | C9: 6536 | D9: sqm | E9: 1060 | F9: =C9*E9 -> 6928160 | K9: =RA!F61 -> 602.56 | L9: =K9*0.05 -> 30.128 | M9: =SUM(H9:L9) -> 632.688 | N9: =M9*C9 -> 4135248.8 | O9: =F9-N9 -> 2792911.2 | P9: =H9*C9 -> 0 | Q9: =I9*C9 -> 0 | R9: =J9*C9 -> 0 | S9: =K9*C9 -> 3938332.2 | T9: =L9*C9 -> 196916.61
A10: 4.03 | B10: Centering with strutting 3-4m height | C10: 739 | D10: sqm | E10: 1095 | F10: =C10*E10 -> 809205 | K10: =RA!F61 -> 602.56 | L10: =K10*0.05 -> 30.128 | M10: =SUM(H10:L10) -> 632.688 | N10: =M10*C10 -> 467556.43 | O10: =F10-N10 -> 341648.57 | P10: =H10*C10 -> 0 | Q10: =I10*C10 -> 0 | R10: =J10*C10 -> 0 | S10: =K10*C10 -> 445291.84 | T10: =L10*C10 -> 22264.592
A11: 4.04 | B11: Centering with strutting 4-5m height | C11: 303 | D11: sqm | E11: 1130 | F11: =C11*E11 -> 342390 | K11: =RA!F67 -> 656.36 | L11: =K11*0.05 -> 32.818 | M11: =SUM(H11:L11) -> 689.178 | N11: =M11*C11 -> 208820.93 | O11: =F11-N11 -> 133569.07 | P11: =H11*C11 -> 0 | Q11: =I11*C11 -> 0 | R11: =J11*C11 -> 0 | S11: =K11*C11 -> 198877.08 | T11: =L11*C11 -> 9943.854
A12: 5 | B12: Providing and placing Plain cement concrete M10 grade using crushed broken hard granite course aggregate (well Graded) of Nominal maximum size of 40mm to Ls specified grading (to achieve the specified characteristicik strength of 10N /mm2 in 28 days) and mixing the ingredients in approved mixer including dewatering of the placement site by baling (pumping and dewatering wherever necess eng placing in layers and vibrating water curing finishing hte surface with all leades and lifts etc. complete complying with Standard Specifications and as directed by the Departmental Engineers. | C12: 379 | D12: cum | E12: 5885 | F12: =C12*E12 -> 2230415 | H12: =RA!F77 -> 2037.4382 | I12: =RA!F86 -> 711.53846 | J12: =RA!F89 -> 268.8 | K12: =RA!F82 -> 550 | L12: =K12*0.05 -> 27.5 | M12: =SUM(H12:L12) -> 3595.2766 | N12: =M12*C12 -> 1362609.8 | O12: =F12-N12 -> 867805.16 | P12: =H12*C12 -> 772189.06 | Q12: =I12*C12 -> 269673.08 | R12: =J12*C12 -> 101875.2 | S12: =K12*C12 -> 208450 | T12: =L12*C12 -> 10422.5
A13: 6 | B13: Providing and placing in position of plain cement concrete M15 using 20 mm size hard blue granite broken stone jelly with M.Sand mixing with mixer machine including the cost of bailing/pumping wherever necessary laying the concrete in layers of not exceeding 15 cm thick, compacting, consolidation, vibratring,finishing, watering, curing etc. complete complying with Standard Specifications and as directed by the Departmental Engineers. | F13: =C13*E13 -> 0 | M13: =SUM(H13:L13) -> 0 | N13: =M13*C13 -> 0 | O13: =F13-N13 -> 0 | P13: =H13*C13 -> 0 | Q13: =I13*C13 -> 0 | R13: =J13*C13 -> 0 | S13: =K13*C13 -> 0 | T13: =L13*C13 -> 0
A14: 6.01 | B14: Below ground level upto 1.50 m | C14: 739 | D14: cum | E14: 6850 | F14: =C14*E14 -> 5062150 | H14: =RA!F101 -> 2287.4382 | I14: =RA!F110 -> 592.94872 | J14: =RA!F113 -> 224 | K14: =RA!F106 -> 550 | L14: =K14*0.05 -> 27.5 | M14: =SUM(H14:L14) -> 3681.8869 | N14: =M14*C14 -> 2720914.4 | O14: =F14-N14 -> 2341235.6 | P14: =H14*C14 -> 1690416.8 | Q14: =I14*C14 -> 438189.1 | R14: =J14*C14 -> 165536 | S14: =K14*C14 -> 406450 | T14: =L14*C14 -> 20322.5
A15: 6.02 | B15: Below ground level-Foundation upto 1.50 m to 4.50 m | C15: 220 | D15: cum | E15: 6984 | F15: =C15*E15 -> 1536480 | H15: =H14 -> 2287.4382 | I15: =I14 -> 592.94872 | J15: =J14 -> 224 | K15: =K14 -> 550 | L15: =K15*0.05 -> 27.5 | M15: =SUM(H15:L15) -> 3681.8869 | N15: =M15*C15 -> 810015.11 | O15: =F15-N15 -> 726464.89 | P15: =H15*C15 -> 503236.4 | Q15: =I15*C15 -> 130448.72 | R15: =J15*C15 -> 49280 | S15: =K15*C15 -> 121000 | T15: =L15*C15 -> 6050
A16: 7 | B16: Providing and placing in position of plain cement concrete M15 grade using 60% of 40mm size hard blue granite broken stone jelly and 40% of 20mm size hard blue granite broken stone jelly with M.Sand mixing with mixer machine including the cost of bailing/pumping wherever necessary laying the concrete in layers of not exceeding 15 cm thick, compacting, consolidation,vibrating,finishing, watering, curing etc. complete complying with Standard Specifications and as directed by the Departmental Engineers. | F16: =C16*E16 -> 0 | M16: =SUM(H16:L16) -> 0 | N16: =M16*C16 -> 0 | O16: =F16-N16 -> 0 | P16: =H16*C16 -> 0 | Q16: =I16*C16 -> 0 | R16: =J16*C16 -> 0 | S16: =K16*C16 -> 0 | T16: =L16*C16 -> 0
A17: 7.01 | B17: Below ground level up to 1.50 m | C17: 4986 | D17: cum | E17: 6510 | F17: =C17*E17 -> 32458860 | H17: =RA!F126 -> 2345.3887 | I17: =RA!F135 -> 711.53846 | J17: =RA!F138 -> 403.2 | K17: =RA!F131 -> 550 | L17: =K17*0.05 -> 27.5 | M17: =SUM(H17:L17) -> 4037.6272 | N17: =M17*C17 -> 20131609 | O17: =F17-N17 -> 12327251 | P17: =H17*C17 -> 11694108 | Q17: =I17*C17 -> 3547730.8 | R17: =J17*C17 -> 2010355.2 | S17: =K17*C17 -> 2742300 | T17: =L17*C17 -> 137115
A18: 7.02 | B18: Above ground level up to 4.50 m | C18: 1579 | D18: cum | E18: 6645 | F18: =C18*E18 -> 10492455 | H18: =H17 -> 2345.3887 | I18: =I17 -> 711.53846 | J18: =J17 -> 403.2 | K18: =K17 -> 550 | L18: =K18*0.05 -> 27.5 | M18: =SUM(H18:L18) -> 4037.6272 | N18: =M18*C18 -> 6375413.3 | O18: =F18-N18 -> 4117041.7 | P18: =H18*C18 -> 3703368.7 | Q18: =I18*C18 -> 1123519.2 | R18: =J18*C18 -> 636652.8 | S18: =K18*C18 -> 868450 | T18: =L18*C18 -> 43422.5
A19: 8 | B19: Supplying and fabrication and CC Block of size 1.50 X 1.50 X 0.90 m with Plain Cement Concrete 1:2:4 (one cement two m.sand and Four aggregate) using 40mm and down graded metal hard broken stone jelly for foundation including dewatering if found necessary and placing in position including ramming watering and curing etc. complete complying with Standard Specifications and as directed by the Departmental Engineers. | C19: 800 | D19: Nos | E19: 14577 | F19: =C19*E19 -> 11661600 | H19: =RA!F151 -> 4918.2465 | I19: =RA!F160 -> 351.37702 | J19: =RA!F163 -> 199.11111 | K19: =RA!F156 -> 1300 | L19: =K19*0.05 -> 65 | M19: =SUM(H19:L19) -> 6833.7346 | N19: =M19*C19 -> 5466987.7 | O19: =F19-N19 -> 6194612.3 | P19: =H19*C19 -> 3934597.2 | Q19: =I19*C19 -> 281101.61 | R19: =J19*C19 -> 159288.89 | S19: =K19*C19 -> 1040000 | T19: =L19*C19 -> 52000
A20: 9 | B20: Providing and laying in position standardised concrete Mix M-20 Grade in accordance with IS 456-2000 using 20mm and downgraded hard broken granite stone jelly for all RCC items of works with minium cement content of 325 kg/m3 and maxium water cement ratio of 0.55 including admixture (Plasticizer/Super plasticizer) in recommended proportions asper IS 9103 to accelerate, retard setting of concrete, improve workability without imparing strength and durability with about (5 cu.m) 7730 kg of 20 mm machine crushed stone jelly and with about (4.79 cu.m) 7670 kg of m.sand, but excluding cost of reinforcemnt grill and fabricating charges, centering and shuttering and also including and laying, vibrating with mechanical vibrators, finishing, curing etc. complete complying with Standard Specifications and as directed by the Departmental Engineers. | C20: 906 | D20: cum | E20: 8709 | F20: =C20*E20 -> 7890354 | H20: =RA!F176 -> 2665.9187 | I20: =RA!F184 -> 711.53846 | J20: =RA!F187 -> 336 | K20: =RA!F180 -> 350 | L20: =K20*0.05 -> 17.5 | M20: =SUM(H20:L20) -> 4080.9572 | N20: =M20*C20 -> 3697347.2 | O20: =F20-N20 -> 4193006.8 | P20: =H20*C20 -> 2415322.4 | Q20: =I20*C20 -> 644653.85 | R20: =J20*C20 -> 304416 | S20: =K20*C20 -> 317100 | T20: =L20*C20 -> 15855
A21: 10 | B21: Reinforced cement concrete M25 using 20mm hard broken stone jelly and downgreded to IS specified grading mixed in mixer machine including dewatering the placement site, laying the concrete in layers and in bays.vibrating compacting and finishing the surface with all lead and lifts, watering curing complete to attain the profile and strength as specified in the drawings and specification for various lengths and heights below and above ground level etc. complete complying with Standard Specifications and as directed by the Departmental Engineers. | C21: 32 | D21: cum | E21: 8857 | F21: =C21*E21 -> 283424 | H21: =RA!F200 -> 2770.9187 | I21: =RA!F208 -> 711.53846 | J21: =RA!F211 -> 336 | K21: =RA!F204 -> 350 | L21: =K21*0.05 -> 17.5 | M21: =SUM(H21:L21) -> 4185.9572 | N21: =M21*C21 -> 133950.63 | O21: =F21-N21 -> 149473.37 | P21: =H21*C21 -> 88669.399 | Q21: =I21*C21 -> 22769.231 | R21: =J21*C21 -> 10752 | S21: =K21*C21 -> 11200 | T21: =L21*C21 -> 560
A22: 11 | B22: Providing and placing plain cement concrete M20 grade using crusher broken hard granite course agrregate (well graded) of nominal maximum size of 20mm to specified grading to achieve the special characteristic strength of 20 N/mm2 in 28 days and mixing the ingredients in approved mixed placing in layers and vibrating water curing finishing the surface with all leads and lifts etc. complete in all respects so as to attain the profile strength specified in the approved drawing and specified in the approved drawing and specifications as per the direction of the engineer incharge of works and etc. complete complying with Standard Specifications and as directed by the Departmental Engineers. | F22: =C22*E22 -> 0 | M22: =SUM(H22:L22) -> 0 | N22: =M22*C22 -> 0 | O22: =F22-N22 -> 0 | P22: =H22*C22 -> 0 | Q22: =I22*C22 -> 0 | R22: =J22*C22 -> 0 | S22: =K22*C22 -> 0 | T22: =L22*C22 -> 0
A23: 11.01 | B23: Below ground level up to 1.50 m | C23: 225 | D23: cum | E23: 7280 | F23: =C23*E23 -> 1638000 | H23: =RA!F224 -> 2665.9187 | I23: =RA!F232 -> 711.53846 | J23: =RA!F235 -> 336 | K23: =RA!F228 -> 350 | L23: =K23*0.05 -> 17.5 | M23: =SUM(H23:L23) -> 4080.9572 | N23: =M23*C23 -> 918215.37 | O23: =F23-N23 -> 719784.63 | P23: =H23*C23 -> 599831.71 | Q23: =I23*C23 -> 160096.15 | R23: =J23*C23 -> 75600 | S23: =K23*C23 -> 78750 | T23: =L23*C23 -> 3937.5
A24: 11.02 | B24: Below ground level 1.50m to upto 4.50 m | C24: 525 | D24: cum | E24: 7414 | F24: =C24*E24 -> 3892350 | H24: =H23 -> 2665.9187 | I24: =I23 -> 711.53846 | J24: =J23 -> 336 | K24: =K23*1.1 -> 385 | L24: =K24*0.05 -> 19.25 | M24: =SUM(H24:L24) -> 4117.7072 | N24: =M24*C24 -> 2161796.3 | O24: =F24-N24 -> 1730553.7 | P24: =H24*C24 -> 1399607.3 | Q24: =I24*C24 -> 373557.69 | R24: =J24*C24 -> 176400 | S24: =K24*C24 -> 202125 | T24: =L24*C24 -> 10106.25
A25: 11.03 | B25: Above ground level upto 4.50m | C25: 2.9 | D25: cum | E25: 7416 | F25: =C25*E25 -> 21506.4 | H25: =H24 -> 2665.9187 | I25: =I24 -> 711.53846 | J25: =J24 -> 336 | K25: =K23*1.2 -> 420 | L25: =K25*0.05 -> 21 | M25: =SUM(H25:L25) -> 4154.4572 | N25: =M25*C25 -> 12047.926 | O25: =F25-N25 -> 9458.4742 | P25: =H25*C25 -> 7731.1643 | Q25: =I25*C25 -> 2063.4615 | R25: =J25*C25 -> 974.4 | S25: =K25*C25 -> 1218 | T25: =L25*C25 -> 60.9
A26: 12 | B26: Supplying fabricating and placing in position of Mild Steel (MS) or Ribbed Tor Steel (RTS) of grills for all R C C works including cost of steel, binding wire and labour charges for decoiling cutting, bending and tying the grills etc. complete complying with standard specifications and as directed by the Departmental Engineers. | C26: 1752 | D26: qtl. | E26: 9258 | F26: =C26*E26 -> 16220016 | H26: =RA!F244 -> 5376 | K26: =RA!F248 -> 1350 | L26: =K26*0.05 -> 67.5 | M26: =SUM(H26:L26) -> 6793.5 | N26: =M26*C26 -> 11902212 | O26: =F26-N26 -> 4317804 | P26: =H26*C26 -> 9418752 | Q26: =I26*C26 -> 0 | R26: =J26*C26 -> 0 | S26: =K26*C26 -> 2365200 | T26: =L26*C26 -> 118260
A27: 13 | B27: Supplying and filling in clean M- sand in layers of not more than 15cm thick well rammed watered and consolidated etc. complete complying with Standard Specifications and as directed by the Departmental Engineers. | C27: 398 | D27: cum | E27: 1785 | F27: =C27*E27 -> 710430 | H27: =RA!F255 -> 742.04947 | I27: =RA!F259 -> 202.93777 | J27: =RA!F262 -> 72.361809 | K27: =RA!F265 -> 200 | M27: =SUM(H27:L27) -> 1217.349 | N27: =M27*C27 -> 484504.92 | O27: =F27-N27 -> 225925.08 | P27: =H27*C27 -> 295335.69 | Q27: =I27*C27 -> 80769.231 | R27: =J27*C27 -> 28800 | S27: =K27*C27 -> 79600 | T27: =L27*C27 -> 0
A28: 14 | B28: Supplying and filling for inverted filter arrangements below CC blocks with 40 cm thick graded inverted filter provided in two or more layers (ie 20 mm, 40 mm, 63 mm.) size metal provided using HBGS jelly conveyance upto 100 m etc. complete complying with Standard Specifications and as directed by the Departmental Engineers. | C28: 795 | D28: cum | E28: 1580 | F28: =C28*E28 -> 1256100 | H28: =RA!F273 -> 1413.4276 | I28: =RA!F278 -> 232.22061 | J28: =RA!F281 -> 207.69811 | K28: =RA!F284 -> 200 | M28: =SUM(H28:L28) -> 2053.3463 | N28: =M28*C28 -> 1632410.3 | O28: =F28-N28 -> -376310.3 | P28: =H28*C28 -> 1123674.9 | Q28: =I28*C28 -> 184615.38 | R28: =J28*C28 -> 165120 | S28: =K28*C28 -> 159000 | T28: =L28*C28 -> 0
A29: 15 | B29: Supplying and Filling of Gravel in between the gap of CC Block with 75mm thick,etc. complete complying with Standard Specifications and as directed by the Departmental Engineers. | C29: 345 | D29: cum | E29: 447 | F29: =C29*E29 -> 154215 | H29: =RA!F293 -> 989.39929 | I29: =RA!F297 -> 75.250836 | J29: =RA!F300 -> 75.130435 | L29: =RA!F303 -> 60.869565 | M29: =SUM(H29:L29) -> 1200.6501 | N29: =M29*C29 -> 414224.29 | O29: =F29-N29 -> -260009.29 | P29: =H29*C29 -> 341342.76 | Q29: =I29*C29 -> 25961.538 | R29: =J29*C29 -> 25920 | S29: =K29*C29 -> 0 | T29: =L29*C29 -> 21000
A30: 16 | B30: Supplying and filling loose boulders of Size more than 300mm and weight more than 40kg in U/S and D/S apron using including conveyance,cost of materials etc. complete complying with standard specifications and as directed by the Departmental Engineers | C30: 4440 | D30: cum | E30: 2614 | F30: =C30*E30 -> 11606160 | H30: =RA!F311 -> 1611.3074 | I30: =RA!F315 -> 72.765073 | J30: =RA!F318 -> 99.891892 | L30: =RA!F321 -> 9.4594595 | M30: =SUM(H30:L30) -> 1793.4238 | N30: =M30*C30 -> 7962801.9 | O30: =F30-N30 -> 3643358.1 | P30: =H30*C30 -> 7154204.9 | Q30: =I30*C30 -> 323076.92 | R30: =J30*C30 -> 443520 | S30: =K30*C30 -> 0 | T30: =L30*C30 -> 42000
A31: 17 | B31: Rough stone dry packing using new stones for cone wrapping aprons and revetment including labour charges etc. complete complying with Standard Specifications and as directed by the Departmental Engineers. (.Cone Wrapping) | C31: 1099 | D31: cum | E31: 2315 | F31: =C31*E31 -> 2544185 | H31: =H30 -> 1611.3074 | I31: =I30 -> 72.765073 | J31: =J30 -> 99.891892 | L31: =L30 -> 9.4594595 | M31: =SUM(H31:L31) -> 1793.4238 | N31: =M31*C31 -> 1970972.8 | O31: =F31-N31 -> 573212.19 | P31: =H31*C31 -> 1770826.9 | Q31: =I31*C31 -> 79968.815 | R31: =J31*C31 -> 109781.19 | S31: =K31*C31 -> 0 | T31: =L31*C31 -> 10395.946
A32: 18 | B32: Jeddy stone packing using new stones u/s stone pitching including labour charges etc. complete complying with Standard Specifications and as directed by the Departmental Engineers. | C32: 450 | D32: cum | E32: 2614 | F32: =C32*E32 -> 1176300 | H32: =H31 -> 1611.3074 | I32: =I31 -> 72.765073 | J32: =J31 -> 99.891892 | L32: =L31 -> 9.4594595 | M32: =SUM(H32:L32) -> 1793.4238 | N32: =M32*C32 -> 807040.73 | O32: =F32-N32 -> 369259.27 | P32: =H32*C32 -> 725088.34 | Q32: =I32*C32 -> 32744.283 | R32: =J32*C32 -> 44951.351 | S32: =K32*C32 -> 0 | T32: =L32*C32 -> 4256.7568
A33: 19 | B33: Design, fabrication, supply, errection, testing and commissioning of fixed wheel type vertical lift gate(with top seal) consisting of skin plate, stiffeners, horizontal and vertical girders, wheels, guide rollers, rubber seals etc., with all accessories for canal escape/regulator vent including cost of materials, machinery, labour, cutting, aligning, welding, finishing, cleaning, applying one coat of zinc rich epoxy primer and three coats of cold applied coal tar epoxy paint,seal fixing etc., complete as per specifications and approved drawings with lead up to 1km and all lifts for structural steel components and all leads and all lifts including packing/forwarding charges for other materials. | C33: 4.44 | D33: tonne | E33: 233491 | F33: =C33*E33 -> 1036700 | K33: =E33*0.5 -> 116745.5 | M33: =SUM(H33:L33) -> 116745.5 | N33: =M33*C33 -> 518350.02 | O33: =F33-N33 -> 518350.02 | P33: =H33*C33 -> 0 | Q33: =I33*C33 -> 0 | R33: =J33*C33 -> 0 | S33: =K33*C33 -> 518350.02 | T33: =L33*C33 -> 0
A34: 20 | B34: Design, fabrication, supply, errection, testing and commissioning of supporting structure, platform, railing, ladder etc., with all accessories for operating canal escape/regulator gate including cost of all materials, machinery, labour, cutting, aligning, welding, finishing, cleaning, greasing, applying two coats of zinc chromate red oxide primer and three coats of approved synthetic enamel paint etc., complete as per specifications and approved drawings with lead up to 1km and all lifts for structural steel components and all leads and all lifts including packing/forwarding charges for other materials. | C34: 3.6 | D34: tonne | E34: 59143 | F34: =C34*E34 -> 212914.8 | K34: =E34*0.5 -> 29571.5 | M34: =SUM(H34:L34) -> 29571.5 | N34: =M34*C34 -> 106457.4 | O34: =F34-N34 -> 106457.4 | P34: =H34*C34 -> 0 | Q34: =I34*C34 -> 0 | R34: =J34*C34 -> 0 | S34: =K34*C34 -> 106457.4 | T34: =L34*C34 -> 0
A35: 21 | B35: Design, fabrication, supply, errection, testing and commissioning of embedded parts (with top seal) consisting of sill beam,wheel tracks,seal seats,guide rails,groove lining upto top etc., with all accessories for vertical lift roller gate for canal escape/regulator including cost of materials, machinery, labour, cutting, aligning, aligning, anchoring, welding, finishing, cleaning, applying one coat of zinc rich epoxy primer and four coats of cold applied coal tar epoxy paint,seal fixing etc., complete as per specifications and approved drawings with lead up to 1km and all lifts for structural steel components and all leads and all lifts including packing/forwarding charges for other materials. | C35: 6.6 | D35: tonne | E35: 243750 | F35: =C35*E35 -> 1608750 | K35: =E35*0.5 -> 121875 | M35: =SUM(H35:L35) -> 121875 | N35: =M35*C35 -> 804375 | O35: =F35-N35 -> 804375 | P35: =H35*C35 -> 0 | Q35: =I35*C35 -> 0 | R35: =J35*C35 -> 0 | S35: =K35*C35 -> 804375 | T35: =L35*C35 -> 0
A36: 22 | B36: Earth work in all soils except hard rock requiring blasting and conveying for formation of bund with lead of 0 to 100 metre with extra lead of 5 km deploying earth moving machinery and tippers including benching, formation of bunds, breaking clods, sectioning etc. complete complying with Standard Specifications and as directed by the Departmental Engineers. | C36: 60000 | D36: cum | E36: 336 | F36: =C36*E36 -> 20160000 | I36: =RA!F332 -> 99.230769 | J36: =RA!F335 -> 20.16 | L36: =RA!F338 -> 4.2 | M36: =SUM(H36:L36) -> 123.59077 | N36: =M36*C36 -> 7415446.2 | O36: =F36-N36 -> 12744554 | P36: =H36*C36 -> 0 | Q36: =I36*C36 -> 5953846.2 | R36: =J36*C36 -> 1209600 | S36: =K36*C36 -> 0 | T36: =L36*C36 -> 252000
A37: 23 | B37: Earthwork Excavation for foundation in all soils and sub soils and to full depth as may be directed except in hard rock requiring blasting inclusive of shoring, strutting and baling out of water wherever necessary refilling the sides of foundation with excavated sand on excavated soil other than sand in layer of 15 cm thick well rammed and consolidated depositing the surplus earth within the compound in places as shown by the departmental officers with initial lead and lift, clearing and leveling the site etc. complete complying with Standard Specifications and as directed by the Departmental Engineers. | C37: 5012 | D37: cum | E37: 106 | F37: =C37*E37 -> 531272 | I37: =RA!F348 -> 48.345509 | J37: =RA!F351 -> 40.223464 | L37: =RA!F354 -> 8.3798883 | M37: =SUM(H37:L37) -> 96.948861 | N37: =M37*C37 -> 485907.69 | O37: =F37-N37 -> 45364.308 | P37: =H37*C37 -> 0 | Q37: =I37*C37 -> 242307.69 | R37: =J37*C37 -> 201600 | S37: =K37*C37 -> 0 | T37: =L37*C37 -> 42000
A38: 24 | B38: Providing and making Gabion structure with Mechanically Woven Double Twisted Hexagonal shaped wire Mesh Gabion Boxes as per IS 16014:2012, Morth Clause 2500, of required size, Mesh Type 10x12 (D=100mm with tolerance of ± 2%) Zinc + PVC Coated, Mesh Wire diameter 2.7 / 3.7mm, mechanically edged / selvedged with partitions at every 1m interval and shall have minimum 10 numbers of openings per meter of mesh perpendicular to twist, tying with lacing wire of diameter 2.2 / 3.2mm (ID/OD), supplied @ 3% by weight of Gabion boxes, filled with boulders with least dimension of 200mm, as per drawing, all complete as per directions of Engineer-in-Charge. | C38: 10038 | D38: cum | E38: 3783 | F38: =C38*E38 -> 37973754 | H38: =RA!F363 -> 2927.0318 | I38: =RA!F367 -> 48.278082 | J38: =RA!F370 -> 66.276151 | K38: =RA!F373 -> 500 | M38: =SUM(H38:L38) -> 3541.586 | N38: =M38*C38 -> 35550441 | O38: =F38-N38 -> 2423313.4 | P38: =H38*C38 -> 29381545 | Q38: =I38*C38 -> 484615.38 | R38: =J38*C38 -> 665280 | S38: =K38*C38 -> 5019000 | T38: =L38*C38 -> 0
A39: 25 | B39: Providing and laying needle punched and mechanically bonded Non-woven Geotextiles of Type-I indigenously manufactured from high quality fibres on the prepared subgrade for separation as per MORTH Specification 702 | C39: 4950 | D39: sqm | E39: 161 | F39: =C39*E39 -> 796950 | H39: =RA!F381 -> 64.56 | K39: =RA!F384 -> 53.8 | M39: =SUM(H39:L39) -> 118.36 | N39: =M39*C39 -> 585882 | O39: =F39-N39 -> 211068 | P39: =H39*C39 -> 319572 | Q39: =I39*C39 -> 0 | R39: =J39*C39 -> 0 | S39: =K39*C39 -> 266310 | T39: =L39*C39 -> 0
A40: 26 | B40: Refilling with excavated soil (other than sand) complying with standard specification for filling in foundation and basement etc. complete complying with Standard Specifications and as directed by the Departmental Engineers. | C40: 4950 | D40: cum | E40: 44 | F40: =C40*E40 -> 217800 | I40: =RA!F393 -> 32.634033 | J40: =RA!F396 -> 34.909091 | L40: =RA!F399 -> 4.2424242 | M40: =SUM(H40:L40) -> 71.785548 | N40: =M40*C40 -> 355338.46 | O40: =F40-N40 -> -137538.46 | P40: =H40*C40 -> 0 | Q40: =I40*C40 -> 161538.46 | R40: =J40*C40 -> 172800 | S40: =K40*C40 -> 0 | T40: =L40*C40 -> 21000
A41: 27 | B41: Earth work excavation for desilting the existing rivers / canals / channels/odai/ nullas / drains/flood bowls/ tanks/ reservoirs etc., consisting of very loose soil, silt, oily silt, slushy, marshy, loany, organic soil, sea shell and flat mica particles with zero present air void in unhygienic & insanitary conditions in under water and not under water deploying earth moving machinery with suitable floats buoys barge/ hydraulic excavator & other mechanical devices including the cost of hire charges for machinery, with cost of skilled operators with helper & cleaners for the entire operations to reach the banks in which the removed silt & sludge has to be dumped over either one of the rivers / canals / channels/odai/ nullas / drains/floods bowls / tanks / reservoirs etc, bank whichever is convenient as per the prevailing site conditions for easy conveyance and including jungle clearance etc.. complete (Rate excluding conveyance to dumping yard or low lying area) | C41: 62994.57 | D41: cum | E41: 109 | F41: =C41*E41 -> 6866408.1 | I41: =RA!F409 -> 25.276904 | J41: =RA!F412 -> 27.979554 | L41: =RA!F415 -> 4.0003448 | M41: =SUM(H41:L41) -> 57.256803 | N41: =M41*C41 -> 3606867.7 | O41: =F41-N41 -> 3259540.4 | P41: =H41*C41 -> 0 | Q41: =I41*C41 -> 1592307.7 | R41: =J41*C41 -> 1762560 | S41: =K41*C41 -> 0 | T41: =L41*C41 -> 252000
A42: 28 | B42: Supplying Demarcation RCC Pre cast Post in Cement Concrete of Grade M15 with well graded aggregates and the nominal maximum size of course aggregate of size 20 mm of size 0.20 x 0.20 x 1.45 M and fixing the Post 40 Cm depth below Ground level, the Post includes using 4 Nos of 10mm RTS Main rod to a length of 1.325 M, using 8 mm MS 10 Nos as Strips with Steel Centring and Painting the Post with Enamel Paint to a Height of 0.80 m around the post etc., complete and Conveying the post to the Site of Demarcation Boundary such as Tank Bund and foreshore including earthwork excavation for Foundation in HSC having the base Plain cement Concrete of 10 Cm of cement concrete M7.5 using Hard blue granite broken stone of graded metal of 40 mm and the Post embeded using Cement Concrete of Grade Cement Concrete M10 with well graded aggregates and the Nominal maximum size of course aggregate of 20 mm etc., complete as directed by the Engineer in charge of works and as per the Technical Specfications | C42: 150 | D42: Nos | E42: 1697 | F42: =C42*E42 -> 254550 | H42: =Materials!E24 -> 1700 | K42: 250 | M42: =SUM(H42:L42) -> 1950 | N42: =M42*C42 -> 292500 | O42: =F42-N42 -> -37950 | P42: =H42*C42 -> 255000 | Q42: =I42*C42 -> 0 | R42: =J42*C42 -> 0 | S42: =K42*C42 -> 37500 | T42: =L42*C42 -> 0
B43: Total = | F43: =SUM(F4:F42) -> 1.9847417e+08 | N43: =SUM(N4:N42) -> 1.2975679e+08 | O43: =SUM(O4:O42) -> 68717385 | P43: =SUM(P4:P42) -> 77594421 | Q43: =SUM(Q4:Q42) -> 17649901 | R43: =SUM(R4:R42) -> 9807271 | S43: =SUM(S4:S42) -> 23076353 | T43: =SUM(T4:T42) -> 1628840.7

Sheet RA
A1: WRO - Varanasi - Ariyalur
A2: Rate Analysis
A3: S.no | B3: Description | C3: Unit | D3: Qty | E3: Rate | F3: Amount
A4: 1 | B4: Clearing Scrub jungle
B5: Output for | C5: Sqm | D5: ='BOQ Major'!C4/17 -> 1520.5647
B6: Machineries
B7: Hire JCB - Day | C7: Day | D7: 1 | E7: 6500 | F7: =PRODUCT(D7:E7) -> 6500
B8: Hire Excavator | C8: Day | D8: 1 | E8: =140000/26 -> 5384.6154 | F8: =PRODUCT(D8:E8) -> 5384.6154 | M8: =40*250 -> 10000
F9: =SUM(F7:F8) -> 11884.615
F10: =F9/$D$5 -> 7.8159222
B11: Fuel
B12: Diesel | C12: Lit | D12: =+(D8*6*9) -> 54 | E12: 96 | F12: =PRODUCT(D12:E12) -> 5184
F13: =F12/D5 -> 3.4092597 | M13: Diesel | N13: =L179/2.5 -> 0 | O13: =N13*96 -> 0
B14: Man Power | M14: Driver | O14: 1000
B15: Helpers | C15: Nos | D15: 1 | E15: 700 | F15: =PRODUCT(D15:E15) -> 700 | M15: Tyre
F16: =F15/D5 -> 0.46035529
B18: Clearing Scrub jungle Total Per Sqm = | F18: =F10+F13+F16 -> 11.685537
A20: 2 | B20: Earthwork
B21: Output for | C21: Cum | D21: ='BOQ Split'!C5/60 -> 87.566667
B22: Machineries
B23: Hire Excavator | C23: Day | D23: 1 | E23: =140000/26 -> 5384.6154 | F23: =PRODUCT(D23:E23) -> 5384.6154
B24: Hire Excavator | C24: Day | D24: 1 | E24: =140000/26 -> 5384.6154 | F24: =PRODUCT(D24:E24) -> 5384.6154
F25: =SUM(F23:F24) -> 10769.231
F26: =F25/D21 -> 122.98322
B27: Fuel
B28: Diesel | C28: Lit | D28: =+(D24*6*8)*2 -> 96 | E28: 96 | F28: =PRODUCT(D28:E28) -> 9216
F29: =F28/D21 -> 105.24553
B30: Man Power
B31: Helpers | C31: Nos | D31: 2 | E31: 700 | F31: =PRODUCT(D31:E31) -> 1400
F32: =F31/D21 -> 15.987819
B34: Earthwork Total Per Cum = | F34: =F26+F29+F32 -> 244.21657
A36: 3 | B36: Earthwork
B37: Output for | C37: Cum | D37: ='BOQ Split'!C6/60 -> 489.68333
B38: Machineries
B39: Hire Excavator | C39: Day | D39: 1 | E39: =140000/26 -> 5384.6154 | F39: =PRODUCT(D39:E39) -> 5384.6154
B40: Hire Excavator | C40: Day | D40: 1 | E40: =140000/26 -> 5384.6154 | F40: =PRODUCT(D40:E40) -> 5384.6154
F41: =SUM(F39:F40) -> 10769.231
F42: =F41/D37 -> 21.992235
B43: Fuel
B44: Diesel | C44: Lit | D44: =+(D40*7*8)*2 -> 112 | E44: 96 | F44: =PRODUCT(D44:E44) -> 10752
F45: =F44/D37 -> 21.957047
B46: Man Power
B47: Helpers | C47: Nos | D47: 2 | E47: 700 | F47: =PRODUCT(D47:E47) -> 1400
F48: =F47/D37 -> 2.8589905
B50: Earthwork Total Per Cum = | F50: =F42+F45+F48 -> 46.808272
A52: 4.01 | B52: Shuttering Ground level
B53: S/C
B54: S/C - Shuttering | C54: Sqm | D54: 1 | E54: =46*10.76 -> 494.96 | F54: =PRODUCT(D54:E54) -> 494.96
B55: Shuttering Total Per Sqm = | F55: =SUM(F54:F54) -> 494.96
A57: 4.02 | B57: Shuttering GL to 3m
B58: S/C
B59: S/C - Shuttering | C59: Sqm | D59: 1 | E59: =50*10.76 -> 538 | F59: =PRODUCT(D59:E59) -> 538
B60: S/C - Staging | C60: Sqm | D60: 1 | E60: =6*10.76 -> 64.56 | F60: =PRODUCT(D60:E60) -> 64.56
B61: Shuttering Total Per Sqm = | F61: =SUM(F59:F60) -> 602.56
A63: 4.04 | B63: Shuttering 4 to 5m
B64: S/C
B65: S/C - Shuttering | C65: Sqm | D65: 1 | E65: =55*10.76 -> 591.8 | F65: =PRODUCT(D65:E65) -> 591.8
B66: S/C - Staging | C66: Sqm | D66: 1 | E66: =6*10.76 -> 64.56 | F66: =PRODUCT(D66:E66) -> 64.56
B67: Shuttering Total Per Sqm = | F67: =SUM(F65:F66) -> 656.36
A69: 5 | B69: PCC M 10
B70: Output for | C70: Cum | D70: 10
B71: Materials
B72: Cement | C72: Bags | D72: 2.5 | E72: =Materials!E9 -> 250 | F72: =PRODUCT(D72:E72) -> 625
B73: River Sand | C73: Unit | D73: =0.55/2.83 -> 0.19434629 | E73: =Materials!E10 -> 800 | F73: =PRODUCT(D73:E73) -> 155.47703
B74: Msand | C74: Unit | D74: =D73*0.05 -> 0.0097173145 | E74: =Materials!E25 -> 6400 | F74: =PRODUCT(D74:E74) -> 62.190813
B75: 40mm | C75: Unit | D75: =0.86/2.83 -> 0.30388693 | E75: =Materials!E11 -> 3800 | F75: =PRODUCT(D75:E75) -> 1154.7703
B76: Water | C76: Lit | D76: 200 | E76: 0.2 | F76: =PRODUCT(D76:E76) -> 40
F77: =SUM(F72:F76) -> 2037.4382
B78: S/C
B79: S/C - Laying | C79: Cum | D79: 1 | E79: 350 | F79: =PRODUCT(D79:E79) -> 350
B80: S/C - Sectioning | C80: Cum | D80: 1 | E80: 200 | F80: =PRODUCT(D80:E80) -> 200
F81: =SUM(F79:F80) -> 550
F82: =F81 -> 550
B83: Machineries
B84: Hire SLM | C84: Day | D84: 1 | E84: =185000/26 -> 7115.3846 | F84: =PRODUCT(D84:E84) -> 7115.3846
F85: =SUM(F84:F84) -> 7115.3846
F86: =F85/D70 -> 711.53846
B87: Fuel
B88: Diesel | C88: Lit | D88: =(D84*4*7) -> 28 | E88: 96 | F88: =PRODUCT(D88:E88) -> 2688
F89: =F88/D70 -> 268.8
B91: for one Cum PCC M10 Total = | F91: =F77+F82+F86+F89 -> 3567.7766
A93: 6 | B93: PCC M 15
B94: Output for | C94: Cum | D94: 12
B95: Materials
B96: Cement | C96: Bags | D96: 3.5 | E96: =E72 -> 250 | F96: =PRODUCT(D96:E96) -> 875
B97: River Sand | C97: Unit | D97: =0.55/2.83 -> 0.19434629 | E97: =E73 -> 800 | F97: =PRODUCT(D97:E97) -> 155.47703
B98: Msand | C98: Unit | D98: =D97*0.05 -> 0.0097173145 | E98: =E74 -> 6400 | F98: =PRODUCT(D98:E98) -> 62.190813
B99: 40mm | C99: Unit | D99: =0.86/2.83 -> 0.30388693 | E99: =E75 -> 3800 | F99: =PRODUCT(D99:E99) -> 1154.7703
B100: Water | C100: Lit | D100: 200 | E100: 0.2 | F100: =PRODUCT(D100:E100) -> 40
F101: =SUM(F96:F100) -> 2287.4382
B102: S/C
B103: S/C - Laying | C103: Cum | D103: 1 | E103: 350 | F103: =PRODUCT(D103:E103) -> 350
B104: S/C - Sectioning | C104: Cum | D104: 1 | E104: 200 | F104: =PRODUCT(D104:E104) -> 200
F105: =SUM(F103:F104) -> 550
F106: =F105 -> 550
B107: Machineries
B108: Hire SLM | C108: Day | D108: 1 | E108: =185000/26 -> 7115.3846 | F108: =PRODUCT(D108:E108) -> 7115.3846
F109: =SUM(F108:F108) -> 7115.3846
F110: =F109/D94 -> 592.94872
B111: Fuel
...

Sheet IDC
B1: Period (months) | C1: 18
B2: Job value | C2: ='BOQ Split'!F43 -> 1.9847417e+08
A4: S.No | B4: DESCRIPTION | C4: Nos | D4: Months | E4: Value (Rs) | F4: Amount | G4: Amount Rs | H4: Rs in Lacs
A5: 1 | B5: Staff Salaries
B6: Designation / Role | C6: Nos | D6: Months | E6: Avg Salary | F6: Amount
B7: Project Engineer | C7: 1 | D7: 12 | E7: 60000 | F7: =PRODUCT(C7:E7) -> 720000
B8: Site Engineer | C8: 4 | D8: 12 | E8: 35000 | F8: =PRODUCT(C8:E8) -> 1680000
B9: Electrician | C9: 2 | D9: 18 | E9: =850*30 -> 25500 | F9: =PRODUCT(C9:E9) -> 918000
B10: TOTAL | C10: =SUM(C7:C9) -> 7 | D10: =SUMPRODUCT(C7:C9,D7:D9) -> 96 | G10: =SUM(F7:F9) -> 3318000 | H10: =+G10/100000 -> 33.18 | I10: =G10/$C$2 -> 0.016717541
A11: =A5+1 -> 2 | B11: Departmental Staff
B12: Dept | C12: 1 | D12: 12 | E12: 50000 | F12: =PRODUCT(C12:E12) -> 600000
B13: TOTAL | C13: =SUM(C12:C12) -> 1 | G13: =SUM(F12:F12) -> 600000 | H13: =+G13/10^5 -> 6 | I13: =G13/$C$2 -> 0.0030230634
A14: =A11+1 -> 3 | B14: PF / Pension / Super Annuation
B15: Bonus for Departmental workmen | C15: =C13 -> 1 | D15: 10 | E15: 10000 | F15: =+E15*C15*D15 -> 100000
B16: TOTAL | G16: =+SUM(F15:F15) -> 100000 | H16: =+G16/10^5 -> 1 | I16: =G16/$C$2 -> 0.0005038439
A17: =A14+1 -> 4 | B17: Welfare & Other Expenses
B18: Guest houses | C18: 1 | D18: 15 | E18: 7500 | F18: =+E18*D18*C18 -> 112500
B19: Furniture for Staff & GH | C19: 1 | D19: 1 | E19: 20000 | F19: =+C19*D19*E19 -> 20000
B20: Air conditioner | C20: 1 | D20: 1 | E20: 50000 | F20: =+C20*D20*E20 -> 50000
B21: Workmen travel Expenses | C21: 1 | D21: 4 | E21: 10000 | F21: 0
B22: GH Helpers | C22: 1 | D22: 12 | E22: 20000 | F22: =+C22*D22*E22 -> 240000
B23: Staff Mobile Expenses | C23: 1 | D23: 6 | E23: 700 | F23: =+C23*D23*E23 -> 4200
B24: Tea / Coffee - Staff | C24: 1 | D24: 12 | E24: 2000 | F24: =+C24*D24*E24 -> 24000
B25: Tea / Coffee - Clients | C25: 1 | D25: 12 | E25: 5000 | F25: =+C25*D25*E25 -> 60000
B26: Snacks / Water | C26: 1 | D26: 12 | E26: 5000 | F26: =+C26*D26*E26 -> 60000
B27: TOTAL | F27: =SUM(F17:F26) -> 570700 | G27: =+F27 -> 570700 | H27: =+G27/10^5 -> 5.707 | I27: =G27/$C$2 -> 0.0028754371
A28: =A17+1 -> 5 | B28: Safety PPEs
B29: Helmet, Shoe, Jacket, | C29: 12 | E29: 1000 | F29: =+E29*C29 -> 12000
B30: TOTAL | F30: =+SUM(F29:F29) -> 12000 | G30: =+F30 -> 12000 | H30: =+G30/10^5 -> 0.12 | I30: =G30/$C$2 -> 6.0461268e-05
A31: =A28+1 -> 6 | B31: Water & Sewage & Power & Fuel
B32: Curing Tank | C32: 1 | D32: 1 | E32: 60000 | F32: =+E32*D32*C32 -> 60000
B33: Sintex for Labour water & office | C33: 1 | D33: 1 | E33: 10000 | F33: =+E33*D33*C33 -> 10000
B34: lights fixtures | C34: 1 | D34: 10 | E34: 1500 | F34: =+E34*D34*C34 -> 15000
B35: cable | C35: 0 | E35: 0.6 | F35: =E35*F34 -> 9000
B36: wire for lighting | C36: 0 | E36: 0.6 | F36: =F35 -> 9000
B37: Power Accessories & Maintenance | C37: 0 | D37: 1 | E37: 1 | F37: 10000
B38: TOTAL | G38: =SUM(F32:F37) -> 113000 | H38: =+G38/10^5 -> 1.13 | I38: =G38/$C$2 -> 0.00056934361
A39: =A31+1 -> 7 | B39: Packing & Forwarding
B40: Local transport expenses | C40: 1 | D40: 12 | E40: 6000 | F40: =+E40*D40*C40 -> 72000
B41: TOTAL | G41: =+SUM(F40:F40) -> 72000 | H41: =+G41/10^5 -> 0.72 | I41: =G41/$C$2 -> 0.00036276761
A42: 8 | B42: Postage & Courier Charges
B43: Postage, paper expenses | C43: 1 | D43: 12 | E43: 400 | F43: =PRODUCT(C43:E43) -> 4800
B44: Desktops | C44: 1 | D44: 1 | E44: 30000 | F44: =PRODUCT(C44:E44) -> 30000
B45: Printer | C45: 1 | D45: 1 | E45: 30000 | F45: =PRODUCT(C45:E45) -> 30000
B46: TOTAL | G46: =SUM(F43:F45) -> 64800 | H46: =+G46/10^5 -> 0.648 | I46: =G46/$C$2 -> 0.00032649085
A47: =A42+1 -> 9 | B47: Repairs & Maintenanace including cleaning & Sweeping & Security service contracts
B48: Labour | C48: 1 | D48: 12 | E48: 18000 | F48: =PRODUCT(C48:E48) -> 216000
B49: Security Deployment | C49: 2 | D49: 12 | E49: 15000 | F49: =PRODUCT(C49:E49) -> 360000
B50: TOTAL | G50: =SUM(F48:F49) -> 576000 | H50: =+G50/10^5 -> 5.76 | I50: =G50/$C$2 -> 0.0029021409
A51: =A47+1 -> 10 | B51: Sundries & Other Expenses
B52: Miscelleneous such as Testing Charges, etc. | C52: 1 | D52: 12 | E52: 7000 | F52: =PRODUCT(C52:E52) -> 84000
B53: Pooja Expenses | C53: 1 | D53: 1 | E53: 50000 | F53: =PRODUCT(C53:E53) -> 50000
B54: mix design | C54: 1 | D54: 8 | E54: 600 | F54: =PRODUCT(C54:E54) -> 4800
B55: lab equipment | C55: 1 | D55: 1 | E55: 100000 | F55: =PRODUCT(C55:E55) -> 100000
B56: TOTAL | G56: =+SUM(F52:F55) -> 238800 | H56: =+G56/10^5 -> 2.388 | I56: =G56/$C$2 -> 0.0012031792
A57: =A51+1 -> 11 | B57: Temporary Structures
B58: Project Office, Labour Shed, Store | C58: 1 | D58: 1 | E58: 300000 | F58: =PRODUCT(C58:E58) -> 300000
B59: Toilet blocks at site | C59: 1 | D59: 1 | E59: 60000 | F59: =PRODUCT(C59:E59) -> 60000
B60: Yard Development | C60: 1 | D60: 1 | E60: 100000 | F60: =PRODUCT(C60:E60) -> 100000
B61: TOTAL | G61: =SUM(F58:F60) -> 460000 | H61: =+G61/10^5 -> 4.6 | I61: =G61/$C$2 -> 0.0023176819
A62: =A57+1 -> 12 | B62: Rentals & Services Charges
B63: Tools | C63: 1 | D63: 12 | E63: 5000 | F63: =PRODUCT(C63:E63) -> 60000
B64: TOTAL | G64: =SUM(F62:F63) -> 60000 | H64: =+G64/10^5 -> 0.6 | I64: =G64/$C$2 -> 0.00030230634
A65: =A62+1 -> 13 | B65: Water and Electricity expenses
B66: Temporary electricity connection | C66: 1 | D66: 1 | E66: 50000 | F66: =PRODUCT(C66:E66) -> 50000
B67: electricity bill - labour camp | C67: 1 | D67: 12 | E67: 7000 | F67: =PRODUCT(C67:E67) -> 84000
B68: guest house | C68: 1 | D68: 15 | E68: 300 | F68: =PRODUCT(C68:E68) -> 4500
B69: TOTAL | G69: =SUM(F66:F68) -> 138500 | H69: =+G69/10^5 -> 1.385 | I69: =G69/$C$2 -> 0.0006978238
A70: 14 | B70: Risk & Contingencies | C70: 0.005 | G70: =C2*C70 -> 992370.85
B71: dewatering | C71: 1 | D71: 12 | E71: 100000 | F71: =PRODUCT(C71:E71) -> 1200000
B72: TOTAL | G72: =SUM(F70:F71)+G70 -> 2192370.9 | H72: =+G72/10^5 -> 21.923709 | I72: =G72/$C$2 -> 0.011046127
A73: 15 | B73: NMR
B74: Unskilled | C74: 30 | D74: 12 | E74: 700 | F74: =PRODUCT(C74:E74) -> 252000
B75: TOTAL | G75: =SUM(F73:F74) -> 252000 | H75: =+G75/10^5 -> 2.52 | I75: =G75/$C$2 -> 0.0012696866
B77: GRAND TOTAL OVERHEADS | G77: =G75+G72+G69+G64+G61+G56+G50+G46+G41+G38+G30+G27+G16+G13+G10 -> 8768170.9 | I77: =G77/$C$2 -> 0.044177894

Sheet Materials
A1: Romaa Infraa Pvt Ltd
A3: Name of Work: | C3: =BOQ!A1 -> Construction of check dam across Marudhaiyar river at Varanavasi village in Ariyalur Taluk and District
A4: Agreement Date : | C4: 45848
A5: Project Duration: | C5: 24 Months | G5: Value of Work
A6: Project Location: | C6: Ariyalur Taluk | G6: =BOQ!F45 -> 2.3419952e+08
A7: MATERIAL LIST
A8: S.No | B8: Description of Materials | C8: Unit | D8: Quantity | E8: Rate / Unit | F8: Rate IncTax | G8: Total Amount | H8: % value in Total Material
A9: 1 | B9: ='BOQ Coeff'!E2 -> Cement | C9: Bags | D9: ='BOQ Coeff'!W43 -> 46788 | E9: 250 | F9: =E9*1.28 -> 320 | G9: =D9*F9 -> 14972160 | H9: =G9/$G$27 -> 0.16388228
A10: 2 | B10: ='BOQ Coeff'!X2 -> River Sand | C10: Unit | D10: ='BOQ Coeff'!X43 -> 2220 | E10: 800 | F10: 800 | G10: =D10*F10 -> 1776000 | H10: =G10/$G$27 -> 0.019439742
A11: 3 | B11: ='BOQ Coeff'!G2 -> 40mm | C11: Unit | D11: ='BOQ Coeff'!Y43 -> 1423 | E11: 3800 | F11: =E11*1.05 -> 3990 | G11: =D11*F11 -> 5677770 | H11: =G11/$G$27 -> 0.062147739
A12: 4 | B12: ='BOQ Coeff'!H2 -> 20mm | C12: Unit | D12: ='BOQ Coeff'!Z43 -> 2145 | E12: 4000 | F12: =E12*1.05 -> 4200 | G12: =D12*F12 -> 9009000 | H12: =G12/$G$27 -> 0.098610719
A13: 5 | B13: M Sand | C13: Unit | D13: =D10*0.1 -> 222 | E13: 5500 | F13: =E13*1.05 -> 5775 | G13: =D13*F13 -> 1282050 | H13: =G13/$G$27 -> 0.014033064
A14: 6 | B14: Dust | C14: Unit | D14: ='BOQ Coeff'!AA43 -> 141 | E14: 4200 | F14: =E14*1.18 -> 4956 | G14: =D14*F14 -> 698796 | H14: =G14/$G$27 -> 0.0076488817
A15: 7 | B15: ='BOQ Coeff'!AB2 -> Mixed - 20,40,60mm | C15: Unit | D15: ='BOQ Coeff'!AB43 -> 281 | E15: 4000 | F15: =E15*1.18 -> 4720 | G15: =D15*F15 -> 1326320 | H15: =G15/$G$27 -> 0.014517634
A16: 8 | B16: ='BOQ Coeff'!AC2 -> Bouldres - Below 300mm | C16: Unit | D16: ='BOQ Coeff'!AC43 -> 4881 | E16: 3800 | F16: =E16*1.18 -> 4484 | G16: =D16*F16 -> 21886404 | H16: =G16/$G$27 -> 0.23956422
A17: 9 | B17: ='BOQ Coeff'!AD2 -> Rough Stone | C17: Unit | D17: ='BOQ Coeff'!AD43 -> 389 | E17: 3800 | F17: =E17*1.05 -> 3990 | G17: =D17*F17 -> 1552110 | H17: =G17/$G$27 -> 0.016989087
A18: 10 | B18: ='BOQ Coeff'!AE2 -> Jeddy Stone | C18: Unit | D18: ='BOQ Coeff'!AE43 -> 160 | E18: 3800 | F18: =E18*1.05 -> 3990 | G18: =D18*F18 -> 638400 | H18: =G18/$G$27 -> 0.0069877992
A19: 11 | B19: ='BOQ Coeff'!AF2 -> TMT Steel | C19: MT | D19: ='BOQ Coeff'!AF43 -> 176 | E19: 50000 | F19: =E19*1.18 -> 59000 | G19: =D19*F19 -> 10384000 | H19: =G19/$G$27 -> 0.11366119
A20: 12 | B20: ='BOQ Coeff'!AG2 -> Vertical Lift Gate | C20: MT | D20: ='BOQ Coeff'!AG43 -> 5 | E20: 100000 | F20: =E20*1.18 -> 118000 | G20: =D20*F20 -> 590000 | H20: =G20/$G$27 -> 0.0064580224
A21: 13 | B21: ='BOQ Coeff'!AH2 -> Structural Steel | C21: MT | D21: ='BOQ Coeff'!AH43 -> 11 | E21: 90000 | F21: =E21*1.18 -> 106200 | G21: =D21*F21 -> 1168200 | H21: =G21/$G$27 -> 0.012786884
A22: 14 | B22: ='BOQ Coeff'!AI2 -> Gravel | C22: Unit | D22: ='BOQ Coeff'!AI43 -> 122 | E22: 2800 | F22: =E22*1.18 -> 3304 | G22: =D22*F22 -> 403088 | H22: =G22/$G$27 -> 0.0044121209
A23: 15 | B23: ='BOQ Coeff'!AJ2 -> needle punched Non-woven Geotextiles | C23: Sqm | D23: ='BOQ Coeff'!AJ43 -> 4950 | E23: =6*10.76 -> 64.56 | F23: =E23*1.18 -> 76.1808 | G23: =D23*F23 -> 377094.96 | H23: =G23/$G$27 -> 0.0041276063
A24: 16 | B24: ='BOQ Coeff'!AK2 -> Precast CC Post - 0.2*0.2*1.45m | C24: Nos | D24: ='BOQ Coeff'!AK43 -> 150 | E24: 1700 | F24: =E24*1.18 -> 2006 | G24: =D24*F24 -> 300900 | H24: =G24/$G$27 -> 0.0032935914
A25: 17 | B25: ='BOQ Coeff'!AL2 -> Shuttering Materials | C25: Sqm | D25: ='BOQ Coeff'!AL43 -> 697 | E25: 6400 | F25: =E25*1.18 -> 7552 | G25: =D25*F25 -> 5263744 | H25: =G25/$G$27 -> 0.057615893
A26: 18 | B26: ='BOQ Coeff'!AM2 -> Hexagonal shaped wire Mesh Gabion Boxes | C26: Sqm | D26: ='BOQ Coeff'!AM43 -> 10038 | E26: 200 | F26: 1400 | G26: =D26*F26 -> 14053200 | H26: =G26/$G$27 -> 0.15382353
B27: Total Amount = | G27: =SUM(G9:G26) -> 91359237 | H27: =(G27/G6) -> 0.39009148
K35: =260+120 -> 380

Sheet BOQ Coeff
A1: =BOQ!A1 -> Construction of check dam across Marudhaiyar river at Varanavasi village in Ariyalur Taluk and District | E1: Co - Efficient | W1: Materials
A2: BOQ | E2: Cement | F2: River Sand | G2: 40mm | H2: 20mm | I2: Dust | J2: Mixed - 20,40,60mm | K2: Bouldres - Below 300mm | L2: Rough Stone | M2: Jeddy Stone | N2: TMT Steel | O2: Vertical Lift Gate | P2: Structural Steel | Q2: Gravel | R2: needle punched Non-woven Geotextiles | S2: Precast CC Post - 0.2*0.2*1.45m | T2: Shuttering Materials | U2: Hexagonal shaped wire Mesh Gabion Boxes | W2: Cement | X2: River Sand | Y2: 40mm | Z2: 20mm | AA2: Dust | AB2: Mixed - 20,40,60mm | AC2: Bouldres - Below 300mm | AD2: Rough Stone | AE2: Jeddy Stone | AF2: TMT Steel | AG2: Vertical Lift Gate | AH2: Structural Steel | AI2: Gravel | AJ2: needle punched Non-woven Geotextiles | AK2: Precast CC Post - 0.2*0.2*1.45m | AL2: Shuttering Materials | AM2: Hexagonal shaped wire Mesh Gabion Boxes
A3: Sno | B3: Item Description | C3: Quantity | D3: Units | E3: Bags | F3: Unit | G3: Unit | H3: Unit | I3: Unit | J3: Unit | N3: MT | O3: Sqm | P3: Kg | Q3: Unit | R3: Sqm | S3: Nos | T3: Sqm | W3: Bags | X3: Unit | Y3: Unit | Z3: Unit | AA3: Unit | AB3: Unit | AC3: Unit | AD3: Unit | AE3: Unit | AF3: MT | AG3: Sqm | AH3: Kg | AI3: Unit | AJ3: Sqm | AK3: Nos | AL3: Sqm | AM3: Nos
A4: 1 | B4: Clearing Scrub jungle and destroying them effectively etc. complete complying with Standard Specifications and as directed by the Departmental Engineers. | C4: 25849.6 | D4: sqm | W4: =C4*E4 -> 0 | X4: =C4*F4 -> 0 | Y4: =C4*G4 -> 0 | Z4: =C4*H4 -> 0 | AA4: =I4*C4 -> 0 | AB4: =J4*C4 -> 0 | AC4: =K4*C4 -> 0 | AD4: =L4*C4 -> 0 | AE4: =M4*C4 -> 0 | AF4: =C4*N4 -> 0 | AG4: =C4*O4 -> 0 | AH4: =C4*P4 -> 0 | AI4: =C4*Q4 -> 0 | AJ4: =R4*C4 -> 0 | AK4: =C4*S4 -> 0 | AL4: =T4*C4 -> 0 | AM4: =U4*C4 -> 0
A5: 2 | B5: Earthwork excavation for foundation in all kind of soils and sub soils to full depth except hardrock,medium rock,requiring blasting inclusive of shoring,strutting and bailing out water wherever necessary,refilling the sides of foundation with excavated earth in layers of not more than 15cm thick well rammed and compacted and depositing the surplus excavated earth in places shown by the departmental officers with initial lead of 10 meters and initial lift of 2 meters clearing and levelling the site complete complying with standard specifications and as directed by the Departmental Engineers. (Narrow excavation) | C5: 5254 | D5: cum | W5: =C5*E5 -> 0 | X5: =C5*F5 -> 0 | Y5: =C5*G5 -> 0 | Z5: =C5*H5 -> 0 | AA5: =I5*C5 -> 0 | AB5: =J5*C5 -> 0 | AC5: =K5*C5 -> 0 | AD5: =L5*C5 -> 0 | AE5: =M5*C5 -> 0 | AF5: =C5*N5 -> 0 | AG5: =C5*O5 -> 0 | AH5: =C5*P5 -> 0 | AI5: =C5*Q5 -> 0 | AJ5: =R5*C5 -> 0 | AK5: =C5*S5 -> 0 | AL5: =T5*C5 -> 0 | AM5: =U5*C5 -> 0
A6: 3 | B6: Earth work excavating and depositing on bank with initial lead of 10 metres and lift of 2 metres in sand silt or other loose soil, wet sand or silt not under water light black cotton soil sandy loam and ordinary soil including excavated earth ordinary soil etc. complete complying with Standard Specifications and as directed by the Departmental Engineers.SS 20 A. (Open Excavation.) | C6: 29381 | D6: cum | W6: =C6*E6 -> 0 | X6: =C6*F6 -> 0 | Y6: =C6*G6 -> 0 | Z6: =C6*H6 -> 0 | AA6: =I6*C6 -> 0 | AB6: =J6*C6 -> 0 | AC6: =K6*C6 -> 0 | AD6: =L6*C6 -> 0 | AE6: =M6*C6 -> 0 | AF6: =C6*N6 -> 0 | AG6: =C6*O6 -> 0 | AH6: =C6*P6 -> 0 | AI6: =C6*Q6 -> 0 | AJ6: =R6*C6 -> 0 | AK6: =C6*S6 -> 0 | AL6: =T6*C6 -> 0 | AM6: =U6*C6 -> 0
A7: 4 | B7: Supplying and erection of steel centering for sides and soffits with strutting up to 3m height for plain surface with all cross bracings using Mild Steel sheets of size 90cm. X 60cm. thickness of and B.G.10 stiffened with welded Mild Steel angles of size 25 X 25 X 3mm for boarding, laid over country wood joists of size 10cmX 6.5cm spaced at 90cm. Centre to centre and supported by casuarina props of 10 to 13cm dia (spaced at 75cm) Centre to centre etc. complete complying with Standard Specifications and as directed by the Departmental Engineers. | W7: =C7*E7 -> 0 | X7: =C7*F7 -> 0 | Y7: =C7*G7 -> 0 | Z7: =C7*H7 -> 0 | AA7: =I7*C7 -> 0 | AB7: =J7*C7 -> 0 | AC7: =K7*C7 -> 0 | AD7: =L7*C7 -> 0 | AE7: =M7*C7 -> 0 | AF7: =C7*N7 -> 0 | AG7: =C7*O7 -> 0 | AH7: =C7*P7 -> 0 | AI7: =C7*Q7 -> 0 | AJ7: =R7*C7 -> 0 | AK7: =C7*S7 -> 0 | AL7: =T7*C7 -> 0 | AM7: =U7*C7 -> 0
A8: 4.01 | B8: Centering without strutting Below ground level | C8: 6346 | D8: sqm | T8: 0.05 | W8: =C8*E8 -> 0 | X8: =C8*F8 -> 0 | Y8: =C8*G8 -> 0 | Z8: =C8*H8 -> 0 | AA8: =I8*C8 -> 0 | AB8: =J8*C8 -> 0 | AC8: =K8*C8 -> 0 | AD8: =L8*C8 -> 0 | AE8: =M8*C8 -> 0 | AF8: =C8*N8 -> 0 | AG8: =C8*O8 -> 0 | AH8: =C8*P8 -> 0 | AI8: =C8*Q8 -> 0 | AJ8: =R8*C8 -> 0 | AK8: =C8*S8 -> 0 | AL8: =T8*C8 -> 317.3 | AM8: =U8*C8 -> 0
A9: 4.02 | B9: Centering with strutting upto 3m height | C9: 6536 | D9: sqm | T9: 0.05 | W9: =C9*E9 -> 0 | X9: =C9*F9 -> 0 | Y9: =C9*G9 -> 0 | Z9: =C9*H9 -> 0 | AA9: =I9*C9 -> 0 | AB9: =J9*C9 -> 0 | AC9: =K9*C9 -> 0 | AD9: =L9*C9 -> 0 | AE9: =M9*C9 -> 0 | AF9: =C9*N9 -> 0 | AG9: =C9*O9 -> 0 | AH9: =C9*P9 -> 0 | AI9: =C9*Q9 -> 0 | AJ9: =R9*C9 -> 0 | AK9: =C9*S9 -> 0 | AL9: =T9*C9 -> 326.8 | AM9: =U9*C9 -> 0
A10: 4.03 | B10: Centering with strutting 3-4m height | C10: 739 | D10: sqm | T10: 0.05 | W10: =C10*E10 -> 0 | X10: =C10*F10 -> 0 | Y10: =C10*G10 -> 0 | Z10: =C10*H10 -> 0 | AA10: =I10*C10 -> 0 | AB10: =J10*C10 -> 0 | AC10: =K10*C10 -> 0 | AD10: =L10*C10 -> 0 | AE10: =M10*C10 -> 0 | AF10: =C10*N10 -> 0 | AG10: =C10*O10 -> 0 | AH10: =C10*P10 -> 0 | AI10: =C10*Q10 -> 0 | AJ10: =R10*C10 -> 0 | AK10: =C10*S10 -> 0 | AL10: =T10*C10 -> 36.95 | AM10: =U10*C10 -> 0
A11: 4.04 | B11: Centering with strutting 4-5m height | C11: 303 | D11: sqm | T11: 0.05 | W11: =C11*E11 -> 0 | X11: =C11*F11 -> 0 | Y11: =C11*G11 -> 0 | Z11: =C11*H11 -> 0 | AA11: =I11*C11 -> 0 | AB11: =J11*C11 -> 0 | AC11: =K11*C11 -> 0 | AD11: =L11*C11 -> 0 | AE11: =M11*C11 -> 0 | AF11: =C11*N11 -> 0 | AG11: =C11*O11 -> 0 | AH11: =C11*P11 -> 0 | AI11: =C11*Q11 -> 0 | AJ11: =R11*C11 -> 0 | AK11: =C11*S11 -> 0 | AL11: =T11*C11 -> 15.15 | AM11: =U11*C11 -> 0
A12: 5 | B12: Providing and placing Plain cement concrete M10 grade using crushed broken hard granite course aggregate (well Graded) of Nominal maximum size of 40mm to Ls specified grading (to achieve the specified characteristicik strength of 10N /mm2 in 28 days) and mixing the ingredients in approved mixer including dewatering of the placement site by baling (pumping and dewatering wherever necess eng placing in layers and vibrating water curing finishing hte surface with all leades and lifts etc. complete complying with Standard Specifications and as directed by the Departmental Engineers. | C12: 379 | D12: cum | E12: 2.5 | F12: =0.56/2.83 -> 0.19787986 | G12: =0.9/2.83 -> 0.3180212 | W12: =C12*E12 -> 947.5 | X12: =C12*F12 -> 74.996466 | Y12: =C12*G12 -> 120.53004 | Z12: =C12*H12 -> 0 | AA12: =I12*C12 -> 0 | AB12: =J12*C12 -> 0 | AC12: =K12*C12 -> 0 | AD12: =L12*C12 -> 0 | AE12: =M12*C12 -> 0 | AF12: =C12*N12 -> 0 | AG12: =C12*O12 -> 0 | AH12: =C12*P12 -> 0 | AI12: =C12*Q12 -> 0 | AJ12: =R12*C12 -> 0 | AK12: =C12*S12 -> 0 | AL12: =T12*C12 -> 0 | AM12: =U12*C12 -> 0
A13: 6 | B13: Providing and placing in position of plain cement concrete M15 using 20 mm size hard blue granite broken stone jelly with M.Sand mixing with mixer machine including the cost of bailing/pumping wherever necessary laying the concrete in layers of not exceeding 15 cm thick, compacting, consolidation, vibratring,finishing, watering, curing etc. complete complying with Standard Specifications and as directed by the Departmental Engineers. | W13: =C13*E13 -> 0 | X13: =C13*F13 -> 0 | Y13: =C13*G13 -> 0 | Z13: =C13*H13 -> 0 | AA13: =I13*C13 -> 0 | AB13: =J13*C13 -> 0 | AC13: =K13*C13 -> 0 | AD13: =L13*C13 -> 0 | AE13: =M13*C13 -> 0 | AF13: =C13*N13 -> 0 | AG13: =C13*O13 -> 0 | AH13: =C13*P13 -> 0 | AI13: =C13*Q13 -> 0 | AJ13: =R13*C13 -> 0 | AK13: =C13*S13 -> 0 | AL13: =T13*C13 -> 0 | AM13: =U13*C13 -> 0
A14: 6.01 | B14: Below ground level upto 1.50 m | C14: 739 | D14: cum | E14: 4 | F14: =0.56/2.83 -> 0.19787986 | H14: =0.9/2.83 -> 0.3180212 | W14: =C14*E14 -> 2956 | X14: =C14*F14 -> 146.23322 | Y14: =C14*G14 -> 0 | Z14: =C14*H14 -> 235.01767 | AA14: =I14*C14 -> 0 | AB14: =J14*C14 -> 0 | AC14: =K14*C14 -> 0 | AD14: =L14*C14 -> 0 | AE14: =M14*C14 -> 0 | AF14: =C14*N14 -> 0 | AG14: =C14*O14 -> 0 | AH14: =C14*P14 -> 0 | AI14: =C14*Q14 -> 0 | AJ14: =R14*C14 -> 0 | AK14: =C14*S14 -> 0 | AL14: =T14*C14 -> 0 | AM14: =U14*C14 -> 0
A15: 6.02 | B15: Below ground level-Foundation upto 1.50 m to 4.50 m | C15: 220 | D15: cum | E15: 4 | F15: =0.56/2.83 -> 0.19787986 | H15: =0.9/2.83 -> 0.3180212 | W15: =C15*E15 -> 880 | X15: =C15*F15 -> 43.533569 | Y15: =C15*G15 -> 0 | Z15: =C15*H15 -> 69.964664 | AA15: =I15*C15 -> 0 | AB15: =J15*C15 -> 0 | AC15: =K15*C15 -> 0 | AD15: =L15*C15 -> 0 | AE15: =M15*C15 -> 0 | AF15: =C15*N15 -> 0 | AG15: =C15*O15 -> 0 | AH15: =C15*P15 -> 0 | AI15: =C15*Q15 -> 0 | AJ15: =R15*C15 -> 0 | AK15: =C15*S15 -> 0 | AL15: =T15*C15 -> 0 | AM15: =U15*C15 -> 0
A16: 7 | B16: Providing and placing in position of plain cement concrete M15 grade using 60% of 40mm size hard blue granite broken stone jelly and 40% of 20mm size hard blue granite broken stone jelly with M.Sand mixing with mixer machine including the cost of bailing/pumping wherever necessary laying the concrete in layers of not exceeding 15 cm thick, compacting, consolidation,vibrating,finishing, watering, curing etc. complete complying with Standard Specifications and as directed by the Departmental Engineers. | W16: =C16*E16 -> 0 | X16: =C16*F16 -> 0 | Y16: =C16*G16 -> 0 | Z16: =C16*H16 -> 0 | AA16: =I16*C16 -> 0 | AB16: =J16*C16 -> 0 | AC16: =K16*C16 -> 0 | AD16: =L16*C16 -> 0 | AE16: =M16*C16 -> 0 | AF16: =C16*N16 -> 0 | AG16: =C16*O16 -> 0 | AH16: =C16*P16 -> 0 | AI16: =C16*Q16 -> 0 | AJ16: =R16*C16 -> 0 | AK16: =C16*S16 -> 0 | AL16: =T16*C16 -> 0 | AM16: =U16*C16 -> 0
A17: 7.01 | B17: Below ground level up to 1.50 m | C17: 4986 | D17: cum | E17: 4 | F17: =0.56/2.83 -> 0.19787986 | G17: =0.9*0.5/2.83 -> 0.1590106 | H17: =0.9*0.5/2.83 -> 0.1590106 | W17: =C17*E17 -> 19944 | X17: =C17*F17 -> 986.62898 | Y17: =C17*G17 -> 792.82686 | Z17: =C17*H17 -> 792.82686 | AA17: =I17*C17 -> 0 | AB17: =J17*C17 -> 0 | AC17: =K17*C17 -> 0 | AD17: =L17*C17 -> 0 | AE17: =M17*C17 -> 0 | AF17: =C17*N17 -> 0 | AG17: =C17*O17 -> 0 | AH17: =C17*P17 -> 0 | AI17: =C17*Q17 -> 0 | AJ17: =R17*C17 -> 0 | AK17: =C17*S17 -> 0 | AL17: =T17*C17 -> 0 | AM17: =U17*C17 -> 0
A18: 7.02 | B18: Above ground level up to 4.50 m | C18: 1579 | D18: cum | E18: 4 | F18: =0.56/2.83 -> 0.19787986 | G18: =0.9*0.5/2.83 -> 0.1590106 | H18: =0.9*0.5/2.83 -> 0.1590106 | W18: =C18*E18 -> 6316 | X18: =C18*F18 -> 312.4523 | Y18: =C18*G18 -> 251.07774 | Z18: =C18*H18 -> 251.07774 | AA18: =I18*C18 -> 0 | AB18: =J18*C18 -> 0 | AC18: =K18*C18 -> 0 | AD18: =L18*C18 -> 0 | AE18: =M18*C18 -> 0 | AF18: =C18*N18 -> 0 | AG18: =C18*O18 -> 0 | AH18: =C18*P18 -> 0 | AI18: =C18*Q18 -> 0 | AJ18: =R18*C18 -> 0 | AK18: =C18*S18 -> 0 | AL18: =T18*C18 -> 0 | AM18: =U18*C18 -> 0
A19: 8 | B19: Supplying and fabrication and CC Block of size 1.50 X 1.50 X 0.90 m with Plain Cement Concrete 1:2:4 (one cement two m.sand and Four aggregate) using 40mm and down graded metal hard broken stone jelly for foundation including dewatering if found necessary and placing in position including ramming watering and curing etc. complete complying with Standard Specifications and as directed by the Departmental Engineers. | C19: 800 | D19: Nos | E19: =1.5*1.5*0.9*4.5 -> 9.1125 | F19: =1.5*1.5*0.9*F18 -> 0.40070671 | G19: =1.5*1.5*0.9*G18 -> 0.32199647 | H19: =1.5*1.5*0.9*H18 -> 0.32199647 | W19: =C19*E19 -> 7290 | X19: =C19*F19 -> 320.56537 | Y19: =C19*G19 -> 257.59717 | Z19: =C19*H19 -> 257.59717 | AA19: =I19*C19 -> 0 | AB19: =J19*C19 -> 0 | AC19: =K19*C19 -> 0 | AD19: =L19*C19 -> 0 | AE19: =M19*C19 -> 0 | AF19: =C19*N19 -> 0 | AG19: =C19*O19 -> 0 | AH19: =C19*P19 -> 0 | AI19: =C19*Q19 -> 0 | AJ19: =R19*C19 -> 0 | AK19: =C19*S19 -> 0 | AL19: =T19*C19 -> 0 | AM19: =U19*C19 -> 0
A20: 9 | B20: Providing and laying in position standardised concrete Mix M-20 Grade in accordance with IS 456-2000 using 20mm and downgraded hard broken granite stone jelly for all RCC items of works with minium cement content of 325 kg/m3 and maxium water cement ratio of 0.55 including admixture (Plasticizer/Super plasticizer) in recommended proportions asper IS 9103 to accelerate, retard setting of concrete, improve workability without imparing strength and durability with about (5 cu.m) 7730 kg of 20 mm machine crushed stone jelly and with about (4.79 cu.m) 7670 kg of m.sand, but excluding cost of reinforcemnt grill and fabricating charges, centering and shuttering and also including and laying, vibrating with mechanical vibrators, finishing, curing etc. complete complying with Standard Specifications and as directed by the Departmental Engineers. | C20: 906 | D20: cum | E20: 5 | F20: =0.56/2.83 -> 0.19787986 | H20: =0.9/2.83 -> 0.3180212 | W20: =C20*E20 -> 4530 | X20: =C20*F20 -> 179.27915 | Y20: =C20*G20 -> 0 | Z20: =C20*H20 -> 288.12721 | AA20: =I20*C20 -> 0 | AB20: =J20*C20 -> 0 | AC20: =K20*C20 -> 0 | AD20: =L20*C20 -> 0 | AE20: =M20*C20 -> 0 | AF20: =C20*N20 -> 0 | AG20: =C20*O20 -> 0 | AH20: =C20*P20 -> 0 | AI20: =C20*Q20 -> 0 | AJ20: =R20*C20 -> 0 | AK20: =C20*S20 -> 0 | AL20: =T20*C20 -> 0 | AM20: =U20*C20 -> 0
A21: 10 | B21: Reinforced cement concrete M25 using 20mm hard broken stone jelly and downgreded to IS specified grading mixed in mixer machine including dewatering the placement site, laying the concrete in layers and in bays.vibrating compacting and finishing the surface with all lead and lifts, watering curing complete to attain the profile and strength as specified in the drawings and specification for various lengths and heights below and above ground level etc. complete complying with Standard Specifications and as directed by the Departmental Engineers. | C21: 32 | D21: cum | E21: 5 | F21: =0.56/2.83 -> 0.19787986 | H21: =0.9/2.83 -> 0.3180212 | W21: =C21*E21 -> 160 | X21: =C21*F21 -> 6.3321555 | Y21: =C21*G21 -> 0 | Z21: =C21*H21 -> 10.176678 | AA21: =I21*C21 -> 0 | AB21: =J21*C21 -> 0 | AC21: =K21*C21 -> 0 | AD21: =L21*C21 -> 0 | AE21: =M21*C21 -> 0 | AF21: =C21*N21 -> 0 | AG21: =C21*O21 -> 0 | AH21: =C21*P21 -> 0 | AI21: =C21*Q21 -> 0 | AJ21: =R21*C21 -> 0 | AK21: =C21*S21 -> 0 | AL21: =T21*C21 -> 0 | AM21: =U21*C21 -> 0
A22: 11 | B22: Providing and placing plain cement concrete M20 grade using crusher broken hard granite course agrregate (well graded) of nominal maximum size of 20mm to specified grading to achieve the special characteristic strength of 20 N/mm2 in 28 days and mixing the ingredients in approved mixed placing in layers and vibrating water curing finishing the surface with all leads and lifts etc. complete in all respects so as to attain the profile strength specified in the approved drawing and specified in the approved drawing and specifications as per the direction of the engineer incharge of works and etc. complete complying with Standard Specifications and as directed by the Departmental Engineers. | W22: =C22*E22 -> 0 | X22: =C22*F22 -> 0 | Y22: =C22*G22 -> 0 | Z22: =C22*H22 -> 0 | AA22: =I22*C22 -> 0 | AB22: =J22*C22 -> 0 | AC22: =K22*C22 -> 0 | AD22: =L22*C22 -> 0 | AE22: =M22*C22 -> 0 | AF22: =C22*N22 -> 0 | AG22: =C22*O22 -> 0 | AH22: =C22*P22 -> 0 | AI22: =C22*Q22 -> 0 | AJ22: =R22*C22 -> 0 | AK22: =C22*S22 -> 0 | AL22: =T22*C22 -> 0 | AM22: =U22*C22 -> 0
A23: 11.01 | B23: Below ground level up to 1.50 m | C23: 225 | D23: cum | E23: 5 | F23: =0.56/2.83 -> 0.19787986 | H23: =0.9/2.83 -> 0.3180212 | W23: =C23*E23 -> 1125 | X23: =C23*F23 -> 44.522968 | Y23: =C23*G23 -> 0 | Z23: =C23*H23 -> 71.55477 | AA23: =I23*C23 -> 0 | AB23: =J23*C23 -> 0 | AC23: =K23*C23 -> 0 | AD23: =L23*C23 -> 0 | AE23: =M23*C23 -> 0 | AF23: =C23*N23 -> 0 | AG23: =C23*O23 -> 0 | AH23: =C23*P23 -> 0 | AI23: =C23*Q23 -> 0 | AJ23: =R23*C23 -> 0 | AK23: =C23*S23 -> 0 | AL23: =T23*C23 -> 0 | AM23: =U23*C23 -> 0
A24: 11.02 | B24: Below ground level 1.50m to upto 4.50 m | C24: 525 | D24: cum | E24: 5 | F24: =0.56/2.83 -> 0.19787986 | H24: =0.9/2.83 -> 0.3180212 | W24: =C24*E24 -> 2625 | X24: =C24*F24 -> 103.88693 | Y24: =C24*G24 -> 0 | Z24: =C24*H24 -> 166.96113 | AA24: =I24*C24 -> 0 | AB24: =J24*C24 -> 0 | AC24: =K24*C24 -> 0 | AD24: =L24*C24 -> 0 | AE24: =M24*C24 -> 0 | AF24: =C24*N24 -> 0 | AG24: =C24*O24 -> 0 | AH24: =C24*P24 -> 0 | AI24: =C24*Q24 -> 0 | AJ24: =R24*C24 -> 0 | AK24: =C24*S24 -> 0 | AL24: =T24*C24 -> 0 | AM24: =U24*C24 -> 0
A25: 11.03 | B25: Above ground level upto 4.50m | C25: 2.9 | D25: cum | E25: 5 | F25: =0.56/2.83 -> 0.19787986 | H25: =0.9/2.83 -> 0.3180212 | W25: =C25*E25 -> 14.5 | X25: =C25*F25 -> 0.57385159 | Y25: =C25*G25 -> 0 | Z25: =C25*H25 -> 0.92226148 | AA25: =I25*C25 -> 0 | AB25: =J25*C25 -> 0 | AC25: =K25*C25 -> 0 | AD25: =L25*C25 -> 0 | AE25: =M25*C25 -> 0 | AF25: =C25*N25 -> 0 | AG25: =C25*O25 -> 0 | AH25: =C25*P25 -> 0 | AI25: =C25*Q25 -> 0 | AJ25: =R25*C25 -> 0 | AK25: =C25*S25 -> 0 | AL25: =T25*C25 -> 0 | AM25: =U25*C25 -> 0
A26: 12 | B26: Supplying fabricating and placing in position of Mild Steel (MS) or Ribbed Tor Steel (RTS) of grills for all R C C works including cost of steel, binding wire and labour charges for decoiling cutting, bending and tying the grills etc. complete complying with standard specifications and as directed by the Departmental Engineers. | C26: 1752 | D26: qtl. | N26: 0.1 | W26: =C26*E26 -> 0 | X26: =C26*F26 -> 0 | Y26: =C26*G26 -> 0 | Z26: =C26*H26 -> 0 | AA26: =I26*C26 -> 0 | AB26: =J26*C26 -> 0 | AC26: =K26*C26 -> 0 | AD26: =L26*C26 -> 0 | AE26: =M26*C26 -> 0 | AF26: =C26*N26 -> 175.2 | AG26: =C26*O26 -> 0 | AH26: =C26*P26 -> 0 | AI26: =C26*Q26 -> 0 | AJ26: =R26*C26 -> 0 | AK26: =C26*S26 -> 0 | AL26: =T26*C26 -> 0 | AM26: =U26*C26 -> 0
A27: 13 | B27: Supplying and filling in clean M- sand in layers of not more than 15cm thick well rammed watered and consolidated etc. complete complying with Standard Specifications and as directed by the Departmental Engineers. | C27: 398 | D27: cum | I27: =1/2.83 -> 0.35335689 | W27: =C27*E27 -> 0 | X27: =C27*F27 -> 0 | Y27: =C27*G27 -> 0 | Z27: =C27*H27 -> 0 | AA27: =I27*C27 -> 140.63604 | AB27: =J27*C27 -> 0 | AC27: =K27*C27 -> 0 | AD27: =L27*C27 -> 0 | AE27: =M27*C27 -> 0 | AF27: =C27*N27 -> 0 | AG27: =C27*O27 -> 0 | AH27: =C27*P27 -> 0 | AI27: =C27*Q27 -> 0 | AJ27: =R27*C27 -> 0 | AK27: =C27*S27 -> 0 | AL27: =T27*C27 -> 0 | AM27: =U27*C27 -> 0
A28: 14 | B28: Supplying and filling for inverted filter arrangements below CC blocks with 40 cm thick graded inverted filter provided in two or more layers (ie 20 mm, 40 mm, 63 mm.) size metal provided using HBGS jelly conveyance upto 100 m etc. complete complying with Standard Specifications and as directed by the Departmental Engineers. | C28: 795 | D28: cum | J28: =1/2.83 -> 0.35335689 | W28: =C28*E28 -> 0 | X28: =C28*F28 -> 0 | Y28: =C28*G28 -> 0 | Z28: =C28*H28 -> 0 | AA28: =I28*C28 -> 0 | AB28: =J28*C28 -> 280.91873 | AC28: =K28*C28 -> 0 | AD28: =L28*C28 -> 0 | AE28: =M28*C28 -> 0 | AF28: =C28*N28 -> 0 | AG28: =C28*O28 -> 0 | AH28: =C28*P28 -> 0 | AI28: =C28*Q28 -> 0 | AJ28: =R28*C28 -> 0 | AK28: =C28*S28 -> 0 | AL28: =T28*C28 -> 0 | AM28: =U28*C28 -> 0
A29: 15 | B29: Supplying and Filling of Gravel in between the gap of CC Block with 75mm thick,etc. complete complying with Standard Specifications and as directed by the Departmental Engineers. | C29: 345 | D29: cum | Q29: =1/2.83 -> 0.35335689 | W29: =C29*E29 -> 0 | X29: =C29*F29 -> 0 | Y29: =C29*G29 -> 0 | Z29: =C29*H29 -> 0 | AA29: =I29*C29 -> 0 | AB29: =J29*C29 -> 0 | AC29: =K29*C29 -> 0 | AD29: =L29*C29 -> 0 | AE29: =M29*C29 -> 0 | AF29: =C29*N29 -> 0 | AG29: =C29*O29 -> 0 | AH29: =C29*P29 -> 0 | AI29: =C29*Q29 -> 121.90813 | AJ29: =R29*C29 -> 0 | AK29: =C29*S29 -> 0 | AL29: =T29*C29 -> 0 | AM29: =U29*C29 -> 0
A30: 16 | B30: Supplying and filling loose boulders of Size more than 300mm and weight more than 40kg in U/S and D/S apron using including conveyance,cost of materials etc. complete complying with standard specifications and as directed by the Departmental Engineers | C30: 4440 | D30: cum | K30: =1/2.83*0.85 -> 0.30035336 | W30: =C30*E30 -> 0 | X30: =C30*F30 -> 0 | Y30: =C30*G30 -> 0 | Z30: =C30*H30 -> 0 | AA30: =I30*C30 -> 0 | AB30: =J30*C30 -> 0 | AC30: =K30*C30 -> 1333.5689 | AD30: =L30*C30 -> 0 | AE30: =M30*C30 -> 0 | AF30: =C30*N30 -> 0 | AG30: =C30*O30 -> 0 | AH30: =C30*P30 -> 0 | AI30: =C30*Q30 -> 0 | AJ30: =R30*C30 -> 0 | AK30: =C30*S30 -> 0 | AL30: =T30*C30 -> 0 | AM30: =U30*C30 -> 0
A31: 17 | B31: Rough stone dry packing using new stones for cone wrapping aprons and revetment including labour charges etc. complete complying with Standard Specifications and as directed by the Departmental Engineers. (.Cone Wrapping) | C31: 1099 | D31: cum | L31: =1/2.83 -> 0.35335689 | W31: =C31*E31 -> 0 | X31: =C31*F31 -> 0 | Y31: =C31*G31 -> 0 | Z31: =C31*H31 -> 0 | AA31: =I31*C31 -> 0 | AB31: =J31*C31 -> 0 | AC31: =K31*C31 -> 0 | AD31: =L31*C31 -> 388.33922 | AE31: =M31*C31 -> 0 | AF31: =C31*N31 -> 0 | AG31: =C31*O31 -> 0 | AH31: =C31*P31 -> 0 | AI31: =C31*Q31 -> 0 | AJ31: =R31*C31 -> 0 | AK31: =C31*S31 -> 0 | AL31: =T31*C31 -> 0 | AM31: =U31*C31 -> 0
A32: 18 | B32: Jeddy stone packing using new stones u/s stone pitching including labour charges etc. complete complying with Standard Specifications and as directed by the Departmental Engineers. | C32: 450 | D32: cum | M32: =1/2.83 -> 0.35335689 | W32: =C32*E32 -> 0 | X32: =C32*F32 -> 0 | Y32: =C32*G32 -> 0 | Z32: =C32*H32 -> 0 | AA32: =I32*C32 -> 0 | AB32: =J32*C32 -> 0 | AC32: =K32*C32 -> 0 | AD32: =L32*C32 -> 0 | AE32: =M32*C32 -> 159.0106 | AF32: =C32*N32 -> 0 | AG32: =C32*O32 -> 0 | AH32: =C32*P32 -> 0 | AI32: =C32*Q32 -> 0 | AJ32: =R32*C32 -> 0 | AK32: =C32*S32 -> 0 | AL32: =T32*C32 -> 0 | AM32: =U32*C32 -> 0
A33: 19 | B33: Design, fabrication, supply, errection, testing and commissioning of fixed wheel type vertical lift gate(with top seal) consisting of skin plate, stiffeners, horizontal and vertical girders, wheels, guide rollers, rubber seals etc., with all accessories for canal escape/regulator vent including cost of materials, machinery, labour, cutting, aligning, welding, finishing, cleaning, applying one coat of zinc rich epoxy primer and three coats of cold applied coal tar epoxy paint,seal fixing etc., complete as per specifications and approved drawings with lead up to 1km and all lifts for structural steel components and all leads and all lifts including packing/forwarding charges for other materials. | C33: 4.44 | D33: tonne | O33: 1 | W33: =C33*E33 -> 0 | X33: =C33*F33 -> 0 | Y33: =C33*G33 -> 0 | Z33: =C33*H33 -> 0 | AA33: =I33*C33 -> 0 | AB33: =J33*C33 -> 0 | AC33: =K33*C33 -> 0 | AD33: =L33*C33 -> 0 | AE33: =M33*C33 -> 0 | AF33: =C33*N33 -> 0 | AG33: =C33*O33 -> 4.44 | AH33: =C33*P33 -> 0 | AI33: =C33*Q33 -> 0 | AJ33: =R33*C33 -> 0 | AK33: =C33*S33 -> 0 | AL33: =T33*C33 -> 0 | AM33: =U33*C33 -> 0
A34: 20 | B34: Design, fabrication, supply, errection, testing and commissioning of supporting structure, platform, railing, ladder etc., with all accessories for operating canal escape/regulator gate including cost of all materials, machinery, labour, cutting, aligning, welding, finishing, cleaning, greasing, applying two coats of zinc chromate red oxide primer and three coats of approved synthetic enamel paint etc., complete as per specifications and approved drawings with lead up to 1km and all lifts for structural steel components and all leads and all lifts including packing/forwarding charges for other materials. | C34: 3.6 | D34: tonne | P34: 1 | W34: =C34*E34 -> 0 | X34: =C34*F34 -> 0 | Y34: =C34*G34 -> 0 | Z34: =C34*H34 -> 0 | AA34: =I34*C34 -> 0 | AB34: =J34*C34 -> 0 | AC34: =K34*C34 -> 0 | AD34: =L34*C34 -> 0 | AE34: =M34*C34 -> 0 | AF34: =C34*N34 -> 0 | AG34: =C34*O34 -> 0 | AH34: =C34*P34 -> 3.6 | AI34: =C34*Q34 -> 0 | AJ34: =R34*C34 -> 0 | AK34: =C34*S34 -> 0 | AL34: =T34*C34 -> 0 | AM34: =U34*C34 -> 0
A35: 21 | B35: Design, fabrication, supply, errection, testing and commissioning of embedded parts (with top seal) consisting of sill beam,wheel tracks,seal seats,guide rails,groove lining upto top etc., with all accessories for vertical lift roller gate for canal escape/regulator including cost of materials, machinery, labour, cutting, aligning, aligning, anchoring, welding, finishing, cleaning, applying one coat of zinc rich epoxy primer and four coats of cold applied coal tar epoxy paint,seal fixing etc., complete as per specifications and approved drawings with lead up to 1km and all lifts for structural steel components and all leads and all lifts including packing/forwarding charges for other materials. | C35: 6.6 | D35: tonne | P35: 1 | W35: =C35*E35 -> 0 | X35: =C35*F35 -> 0 | Y35: =C35*G35 -> 0 | Z35: =C35*H35 -> 0 | AA35: =I35*C35 -> 0 | AB35: =J35*C35 -> 0 | AC35: =K35*C35 -> 0 | AD35: =L35*C35 -> 0 | AE35: =M35*C35 -> 0 | AF35: =C35*N35 -> 0 | AG35: =C35*O35 -> 0 | AH35: =C35*P35 -> 6.6 | AI35: =C35*Q35 -> 0 | AJ35: =R35*C35 -> 0 | AK35: =C35*S35 -> 0 | AL35: =T35*C35 -> 0 | AM35: =U35*C35 -> 0
A36: 22 | B36: Earth work in all soils except hard rock requiring blasting and conveying for formation of bund with lead of 0 to 100 metre with extra lead of 5 km deploying earth moving machinery and tippers including benching, formation of bunds, breaking clods, sectioning etc. complete complying with Standard Specifications and as directed by the Departmental Engineers. | C36: 60000 | D36: cum | W36: =C36*E36 -> 0 | X36: =C36*F36 -> 0 | Y36: =C36*G36 -> 0 | Z36: =C36*H36 -> 0 | AA36: =I36*C36 -> 0 | AB36: =J36*C36 -> 0 | AC36: =K36*C36 -> 0 | AD36: =L36*C36 -> 0 | AE36: =M36*C36 -> 0 | AF36: =C36*N36 -> 0 | AG36: =C36*O36 -> 0 | AH36: =C36*P36 -> 0 | AI36: =C36*Q36 -> 0 | AJ36: =R36*C36 -> 0 | AK36: =C36*S36 -> 0 | AL36: =T36*C36 -> 0 | AM36: =U36*C36 -> 0
A37: 23 | B37: Earthwork Excavation for foundation in all soils and sub soils and to full depth as may be directed except in hard rock requiring blasting inclusive of shoring, strutting and baling out of water wherever necessary refilling the sides of foundation with excavated sand on excavated soil other than sand in layer of 15 cm thick well rammed and consolidated depositing the surplus earth within the compound in places as shown by the departmental officers with initial lead and lift, clearing and leveling the site etc. complete complying with Standard Specifications and as directed by the Departmental Engineers. | C37: 5012 | D37: cum | W37: =C37*E37 -> 0 | X37: =C37*F37 -> 0 | Y37: =C37*G37 -> 0 | Z37: =C37*H37 -> 0 | AA37: =I37*C37 -> 0 | AB37: =J37*C37 -> 0 | AC37: =K37*C37 -> 0 | AD37: =L37*C37 -> 0 | AE37: =M37*C37 -> 0 | AF37: =C37*N37 -> 0 | AG37: =C37*O37 -> 0 | AH37: =C37*P37 -> 0 | AI37: =C37*Q37 -> 0 | AJ37: =R37*C37 -> 0 | AK37: =C37*S37 -> 0 | AL37: =T37*C37 -> 0 | AM37: =U37*C37 -> 0
A38: 24 | B38: Providing and making Gabion structure with Mechanically Woven Double Twisted Hexagonal shaped wire Mesh Gabion Boxes as per IS 16014:2012, Morth Clause 2500, of required size, Mesh Type 10x12 (D=100mm with tolerance of ± 2%) Zinc + PVC Coated, Mesh Wire diameter 2.7 / 3.7mm, mechanically edged / selvedged with partitions at every 1m interval and shall have minimum 10 numbers of openings per meter of mesh perpendicular to twist, tying with lacing wire of diameter 2.2 / 3.2mm (ID/OD), supplied @ 3% by weight of Gabion boxes, filled with boulders with least dimension of 200mm, as per drawing, all complete as per directions of Engineer-in-Charge. | C38: 10038 | D38: cum | K38: =1/2.83 -> 0.35335689 | U38: 1 | W38: =C38*E38 -> 0 | X38: =C38*F38 -> 0 | Y38: =C38*G38 -> 0 | Z38: =C38*H38 -> 0 | AA38: =I38*C38 -> 0 | AB38: =J38*C38 -> 0 | AC38: =K38*C38 -> 3546.9965 | AD38: =L38*C38 -> 0 | AE38: =M38*C38 -> 0 | AF38: =C38*N38 -> 0 | AG38: =C38*O38 -> 0 | AH38: =C38*P38 -> 0 | AI38: =C38*Q38 -> 0 | AJ38: =R38*C38 -> 0 | AK38: =C38*S38 -> 0 | AL38: =T38*C38 -> 0 | AM38: =U38*C38 -> 10038
A39: 25 | B39: Providing and laying needle punched and mechanically bonded Non-woven Geotextiles of Type-I indigenously manufactured from high quality fibres on the prepared subgrade for separation as per MORTH Specification 702 | C39: 4950 | D39: sqm | R39: 1 | W39: =C39*E39 -> 0 | X39: =C39*F39 -> 0 | Y39: =C39*G39 -> 0 | Z39: =C39*H39 -> 0 | AA39: =I39*C39 -> 0 | AB39: =J39*C39 -> 0 | AC39: =K39*C39 -> 0 | AD39: =L39*C39 -> 0 | AE39: =M39*C39 -> 0 | AF39: =C39*N39 -> 0 | AG39: =C39*O39 -> 0 | AH39: =C39*P39 -> 0 | AI39: =C39*Q39 -> 0 | AJ39: =R39*C39 -> 4950 | AK39: =C39*S39 -> 0 | AL39: =T39*C39 -> 0 | AM39: =U39*C39 -> 0
A40: 26 | B40: Refilling with excavated soil (other than sand) complying with standard specification for filling in foundation and basement etc. complete complying with Standard Specifications and as directed by the Departmental Engineers. | C40: 4950 | D40: cum | W40: =C40*E40 -> 0 | X40: =C40*F40 -> 0 | Y40: =C40*G40 -> 0 | Z40: =C40*H40 -> 0 | AA40: =I40*C40 -> 0 | AB40: =J40*C40 -> 0 | AC40: =K40*C40 -> 0 | AD40: =L40*C40 -> 0 | AE40: =M40*C40 -> 0 | AF40: =C40*N40 -> 0 | AG40: =C40*O40 -> 0 | AH40: =C40*P40 -> 0 | AI40: =C40*Q40 -> 0 | AJ40: =R40*C40 -> 0 | AK40: =C40*S40 -> 0 | AL40: =T40*C40 -> 0 | AM40: =U40*C40 -> 0
A41: 27 | B41: Earth work excavation for desilting the existing rivers / canals / channels/odai/ nullas / drains/flood bowls/ tanks/ reservoirs etc., consisting of very loose soil, silt, oily silt, slushy, marshy, loany, organic soil, sea shell and flat mica particles with zero present air void in unhygienic & insanitary conditions in under water and not under water deploying earth moving machinery with suitable floats buoys barge/ hydraulic excavator & other mechanical devices including the cost of hire charges for machinery, with cost of skilled operators with helper & cleaners for the entire operations to reach the banks in which the removed silt & sludge has to be dumped over either one of the rivers / canals / channels/odai/ nullas / drains/floods bowls / tanks / reservoirs etc, bank whichever is convenient as per the prevailing site conditions for easy conveyance and including jungle clearance etc.. complete (Rate excluding conveyance to dumping yard or low lying area) | C41: 62994.57 | D41: cum | W41: =C41*E41 -> 0 | X41: =C41*F41 -> 0 | Y41: =C41*G41 -> 0 | Z41: =C41*H41 -> 0 | AA41: =I41*C41 -> 0 | AB41: =J41*C41 -> 0 | AC41: =K41*C41 -> 0 | AD41: =L41*C41 -> 0 | AE41: =M41*C41 -> 0 | AF41: =C41*N41 -> 0 | AG41: =C41*O41 -> 0 | AH41: =C41*P41 -> 0 | AI41: =C41*Q41 -> 0 | AJ41: =R41*C41 -> 0 | AK41: =C41*S41 -> 0 | AL41: =T41*C41 -> 0 | AM41: =U41*C41 -> 0
A42: 28 | B42: Supplying Demarcation RCC Pre cast Post in Cement Concrete of Grade M15 with well graded aggregates and the nominal maximum size of course aggregate of size 20 mm of size 0.20 x 0.20 x 1.45 M and fixing the Post 40 Cm depth below Ground level, the Post includes using 4 Nos of 10mm RTS Main rod to a length of 1.325 M, using 8 mm MS 10 Nos as Strips with Steel Centring and Painting the Post with Enamel Paint to a Height of 0.80 m around the post etc., complete and Conveying the post to the Site of Demarcation Boundary such as Tank Bund and foreshore including earthwork excavation for Foundation in HSC having the base Plain cement Concrete of 10 Cm of cement concrete M7.5 using Hard blue granite broken stone of graded metal of 40 mm and the Post embeded using Cement Concrete of Grade Cement Concrete M10 with well graded aggregates and the Nominal maximum size of course aggregate of 20 mm etc., complete as directed by the Engineer in charge of works and as per the Technical Specfications | C42: 150 | D42: Nos | S42: 1 | W42: =C42*E42 -> 0 | X42: =C42*F42 -> 0 | Y42: =C42*G42 -> 0 | Z42: =C42*H42 -> 0 | AA42: =I42*C42 -> 0 | AB42: =J42*C42 -> 0 | AC42: =K42*C42 -> 0 | AD42: =L42*C42 -> 0 | AE42: =M42*C42 -> 0 | AF42: =C42*N42 -> 0 | AG42: =C42*O42 -> 0 | AH42: =C42*P42 -> 0 | AI42: =C42*Q42 -> 0 | AJ42: =R42*C42 -> 0 | AK42: =C42*S42 -> 150 | AL42: =T42*C42 -> 0 | AM42: =U42*C42 -> 0
W43: =ROUNDUP(SUM(W4:W42),0) -> 46788 | X43: =ROUNDUP(SUM(X4:X42),0) -> 2220 | Y43: =ROUNDUP(SUM(Y4:Y42),0) -> 1423 | Z43: =ROUNDUP(SUM(Z4:Z42),0) -> 2145 | AA43: =ROUNDUP(SUM(AA4:AA42),0) -> 141 | AB43: =ROUNDUP(SUM(AB4:AB42),0) -> 281 | AC43: =ROUNDUP(SUM(AC4:AC42),0) -> 4881 | AD43: =ROUNDUP(SUM(AD4:AD42),0) -> 389 | ... AM43: =ROUNDUP(SUM(AM4:AM42),0) -> 10038
F44: 2310
F45: =F44/C38 -> 0.23012552

Sheet Sheet1
A1: RA - Ajax - Concrete - Silver Beach - ECR
A3: Ajax - Rate Analysis
A4: S.no | B4: Description | C4: Unit | D4: Qty | E4: Rate | F4: Amount
A5: 1 | B5: RCC M30
B6: Output for | C6: Cum | D6: 24
B7: Materials
B8: Cement | C8: Bags | D8: 6.5 | E8: 270 | F8: =PRODUCT(D8:E8) -> 1755 | I8: =320/1.18 -> 271.18644 | J8: Msand | K8: 20mm
B9: Msand | C9: Unit | D9: =0.55/2.83 -> 0.19434629 | E9: 7500 | F9: =PRODUCT(D9:E9) -> 1457.5972 | J9: =950+650 -> 1600 | K9: =550+650 -> 1200
B10: 20mm | C10: Unit | D10: =0.88/2.83 -> 0.31095406 | E10: 5600 | F10: =PRODUCT(D10:E10) -> 1741.3428 | J10: =J9*1.65 -> 2640 | K10: =K9*1.65 -> 1980
B11: Water | C11: Lit | D11: 200 | E11: 0.2 | F11: =PRODUCT(D11:E11) -> 40 | J11: =J10*2.83 -> 7471.2 | K11: =K10*2.83 -> 5603.4
F12: =SUM(F8:F11) -> 4993.9399
B13: Labour
B14: Cement Bag | C14: Bags | D14: 6.5 | E14: 10 | F14: =PRODUCT(D14:E14) -> 65
F15: =SUM(F14:F14) -> 65
F16: =F15 -> 65
B17: Machineries
B18: Hire SLM | C18: Day | D18: 1 | E18: =185000/26 -> 7115.3846 | F18: =PRODUCT(D18:E18) -> 7115.3846
F19: =SUM(F18:F18) -> 7115.3846
F20: =F19/D6 -> 296.47436
B21: Fuel
B22: Diesel | C22: Lit | D22: =(D18*7*7) -> 49 | E22: 96 | F22: =PRODUCT(D22:E22) -> 4704
F23: =F22/D6 -> 196
B25: for one Cum RCC M30 Total = | F25: =F12+F16+F20+F23 -> 5551.4143
B28: For M30 Concrete
B29: Using Ajax Mix - | F29: 5450
B30: Using RMC Mix - | F30: 5450
B32: For M35 Concrete
B33: Using Ajax Mix - | F33: 5550
B34: Using RMC Mix - | F34: 5550
